{
  "type": "Feature",
  "properties": {
    "gn:admin1_code":"06",
    "gn:asciiname":"Felfele",
    "gn:country_code":"ER",
    "gn:dem":1173,
    "gn:feature_class":"P",
    "gn:feature_code":"PPL",
    "gn:name":"Felfele",
    "gn:population":0,
    "gn:timezone":"Africa/Asmara",
    "iso:country":"ER",
    "name:und_x_variant":[
        "Fil File",
        "Felfele"
    ],
    "wof:name":"Felfele",
    "wof:placetype":"locality"
},
  "geometry": {"coordinates":[38.39337,16.0229],"type":"Point"}
}