{
  "type": "Feature",
  "properties": {
    "gn:admin1_code":"05",
    "gn:asciiname":"Zagr",
    "gn:country_code":"ER",
    "gn:dem":2577,
    "gn:feature_class":"P",
    "gn:feature_code":"PPL",
    "gn:name":"Zagr",
    "gn:population":0,
    "gn:timezone":"Africa/Asmara",
    "iso:country":"ER",
    "name:und_x_variant":[
        "Zagher",
        "Zagr"
    ],
    "wof:name":"Zagr",
    "wof:placetype":"locality"
},
  "geometry": {"coordinates":[38.89706,15.53965],"type":"Point"}
}