{
  "type": "Feature",
  "properties": {
    "gn:admin1_code":"02",
    "gn:asciiname":"Adi Lagen",
    "gn:country_code":"ER",
    "gn:dem":1736,
    "gn:feature_class":"P",
    "gn:feature_code":"PPL",
    "gn:name":"Adi Lagen",
    "gn:population":0,
    "gn:timezone":"Africa/Asmara",
    "iso:country":"ER",
    "wof:name":"Adi Lagen",
    "wof:placetype":"locality"
},
  "geometry": {"coordinates":[38.63111,14.75694],"type":"Point"}
}