{
  "type": "Feature",
  "properties": {
    "gn:admin1_code":"02",
    "gn:asciiname":"Bete Ts'iyon",
    "gn:country_code":"ER",
    "gn:dem":2135,
    "gn:feature_class":"P",
    "gn:feature_code":"PPL",
    "gn:name":"B\u0113te Ts\u2019iyon",
    "gn:population":0,
    "gn:timezone":"Africa/Asmara",
    "iso:country":"ER",
    "name:und_x_variant":[
        "Bete Tsyion",
        "B\u0113te Ts\u2019iyon"
    ],
    "wof:name":"Bete Ts'iyon",
    "wof:placetype":"locality"
},
  "geometry": {"coordinates":[38.84333,14.565],"type":"Point"}
}