{
  "type": "Feature",
  "properties": {
    "gn:admin1_code":"02",
    "gn:asciiname":"Adi Zarna",
    "gn:country_code":"ER",
    "gn:dem":1977,
    "gn:feature_class":"P",
    "gn:feature_code":"PPL",
    "gn:name":"\u0100d\u012b Zarna",
    "gn:population":0,
    "gn:timezone":"Africa/Asmara",
    "iso:country":"ER",
    "name:und_x_variant":[
        "Aregit Azerna",
        "\u0100d\u012b Zarna"
    ],
    "wof:name":"Adi Zarna",
    "wof:placetype":"locality"
},
  "geometry": {"coordinates":[38.83639,14.92833],"type":"Point"}
}