{
  "type": "Feature",
  "properties": {
    "gn:admin1_code":"01",
    "gn:asciiname":"Gulgul",
    "gn:country_code":"ER",
    "gn:dem":2263,
    "gn:feature_class":"P",
    "gn:feature_code":"PPL",
    "gn:name":"Gulgul",
    "gn:population":0,
    "gn:timezone":"Africa/Asmara",
    "iso:country":"ER",
    "wof:name":"Gulgul",
    "wof:placetype":"locality"
},
  "geometry": {"coordinates":[38.79083,15.58167],"type":"Point"}
}