{
  "type": "Feature",
  "properties": {
    "gn:admin1_code":"00",
    "gn:asciiname":"Debe'aluwa",
    "gn:country_code":"ER",
    "gn:dem":15,
    "gn:feature_class":"P",
    "gn:feature_code":"PPL",
    "gn:name":"Debe\u2019\u0101luwa",
    "gn:population":0,
    "gn:timezone":"Africa/Asmara",
    "iso:country":"ER",
    "name:und_x_variant":[
        "Dubellu",
        "Dhu Bellu",
        "Debe\u2019\u0101luwa"
    ],
    "wof:name":"Debe'aluwa",
    "wof:placetype":"locality"
},
  "geometry": {"coordinates":[40.11667,15.74361],"type":"Point"}
}