{
  "type": "Feature",
  "properties": {
    "gn:admin1_code":"02",
    "gn:asciiname":"Torat",
    "gn:country_code":"ER",
    "gn:dem":1990,
    "gn:feature_class":"P",
    "gn:feature_code":"PPL",
    "gn:name":"Torat",
    "gn:population":0,
    "gn:timezone":"Africa/Asmara",
    "iso:country":"ER",
    "wof:name":"Torat",
    "wof:placetype":"locality"
},
  "geometry": {"coordinates":[38.90166,15.06944],"type":"Point"}
}