{
  "type": "Feature",
  "properties": {
    "gn:admin1_code":"00",
    "gn:asciiname":"Gurgur",
    "gn:country_code":"ER",
    "gn:dem":1920,
    "gn:feature_class":"P",
    "gn:feature_code":"PPL",
    "gn:name":"Gurgur",
    "gn:population":0,
    "gn:timezone":"Africa/Asmara",
    "iso:country":"ER",
    "wof:name":"Gurgur",
    "wof:placetype":"locality"
},
  "geometry": {"coordinates":[39.36083,14.66083],"type":"Point"}
}