{
  "type": "Feature",
  "properties": {
    "gn:admin1_code":"00",
    "gn:asciiname":"Aligider",
    "gn:cc2":"ER",
    "gn:country_code":"ER",
    "gn:dem":558,
    "gn:feature_class":"P",
    "gn:feature_code":"PPL",
    "gn:name":"Aligider",
    "gn:population":0,
    "gn:timezone":"Africa/Asmara",
    "iso:country":"ER",
    "name:und_x_variant":[
        "Aligidir",
        "Aligider"
    ],
    "wof:name":"Aligider",
    "wof:placetype":"locality"
},
  "geometry": {"coordinates":[36.48333,15.11667],"type":"Point"}
}