{
  "type": "Feature",
  "properties": {
    "gn:admin1_code":"02",
    "gn:asciiname":"Adi Arkay",
    "gn:country_code":"ER",
    "gn:dem":1987,
    "gn:feature_class":"P",
    "gn:feature_code":"PPL",
    "gn:name":"Adi Arkay",
    "gn:population":0,
    "gn:timezone":"Africa/Asmara",
    "iso:country":"ER",
    "wof:name":"Adi Arkay",
    "wof:placetype":"locality"
},
  "geometry": {"coordinates":[38.87194,14.69028],"type":"Point"}
}