{
  "type": "Feature",
  "properties": {
    "gn:admin1_code":"04",
    "gn:asciiname":"Ad Amiyey",
    "gn:country_code":"ER",
    "gn:dem":785,
    "gn:feature_class":"P",
    "gn:feature_code":"PPL",
    "gn:name":"Ad Amiyey",
    "gn:population":0,
    "gn:timezone":"Africa/Asmara",
    "iso:country":"ER",
    "wof:name":"Ad Amiyey",
    "wof:placetype":"locality"
},
  "geometry": {"coordinates":[38.34223,15.50886],"type":"Point"}
}