{
  "type": "Feature",
  "properties": {
    "gn:admin1_code":"02",
    "gn:asciiname":"Adi Tafa",
    "gn:country_code":"ER",
    "gn:dem":1978,
    "gn:feature_class":"P",
    "gn:feature_code":"PPL",
    "gn:name":"Adi Tafa",
    "gn:population":0,
    "gn:timezone":"Africa/Asmara",
    "iso:country":"ER",
    "wof:name":"Adi Tafa",
    "wof:placetype":"locality"
},
  "geometry": {"coordinates":[38.89389,14.70806],"type":"Point"}
}