{
  "type": "Feature",
  "properties": {
    "gn:admin1_code":"05",
    "gn:asciiname":"Ad Doshe",
    "gn:country_code":"ER",
    "gn:dem":2216,
    "gn:feature_class":"P",
    "gn:feature_code":"PPL",
    "gn:name":"Ad Doshe",
    "gn:population":0,
    "gn:timezone":"Africa/Asmara",
    "iso:country":"ER",
    "wof:name":"Ad Doshe",
    "wof:placetype":"locality"
},
  "geometry": {"coordinates":[38.944,15.22885],"type":"Point"}
}