{
  "type": "Feature",
  "properties": {
    "gn:admin1_code":"02",
    "gn:asciiname":"Karran Kudo",
    "gn:country_code":"ER",
    "gn:dem":1981,
    "gn:feature_class":"P",
    "gn:feature_code":"PPL",
    "gn:name":"Karran Kudo",
    "gn:population":0,
    "gn:timezone":"Africa/Asmara",
    "iso:country":"ER",
    "wof:name":"Karran Kudo",
    "wof:placetype":"locality"
},
  "geometry": {"coordinates":[38.80028,14.88667],"type":"Point"}
}