{
  "type": "Feature",
  "properties": {
    "gn:admin1_code":"04",
    "gn:asciiname":"Bambene",
    "gn:country_code":"ER",
    "gn:dem":980,
    "gn:feature_class":"P",
    "gn:feature_code":"PPL",
    "gn:name":"Bambene",
    "gn:population":0,
    "gn:timezone":"Africa/Asmara",
    "iso:country":"ER",
    "wof:name":"Bambene",
    "wof:placetype":"locality"
},
  "geometry": {"coordinates":[37.35848,15.29624],"type":"Point"}
}