{
  "type": "Feature",
  "properties": {
    "gn:admin1_code":"02",
    "gn:asciiname":"Ad Zeban Sebao",
    "gn:country_code":"ER",
    "gn:dem":1760,
    "gn:feature_class":"P",
    "gn:feature_code":"PPL",
    "gn:name":"Ad Zeban Sebao",
    "gn:population":0,
    "gn:timezone":"Africa/Asmara",
    "iso:country":"ER",
    "name:und_x_variant":[
        "Adi Zeban Sebas",
        "Ad Zeban Sebao"
    ],
    "wof:name":"Ad Zeban Sebao",
    "wof:placetype":"locality"
},
  "geometry": {"coordinates":[38.74667,14.78194],"type":"Point"}
}