{
  "type": "Feature",
  "properties": {
    "gn:admin1_code":"04",
    "gn:asciiname":"Vogeriko",
    "gn:country_code":"ER",
    "gn:dem":2171,
    "gn:feature_class":"P",
    "gn:feature_code":"PPL",
    "gn:name":"Vogeriko",
    "gn:population":0,
    "gn:timezone":"Africa/Asmara",
    "iso:country":"ER",
    "wof:name":"Vogeriko",
    "wof:placetype":"locality"
},
  "geometry": {"coordinates":[38.68125,15.24146],"type":"Point"}
}