{
  "type": "Feature",
  "properties": {
    "gn:admin1_code":"00",
    "gn:asciiname":"Dangrigba",
    "gn:country_code":"ER",
    "gn:dem":2248,
    "gn:feature_class":"P",
    "gn:feature_code":"PPL",
    "gn:name":"Dangrigba",
    "gn:population":0,
    "gn:timezone":"Africa/Asmara",
    "iso:country":"ER",
    "wof:name":"Dangrigba",
    "wof:placetype":"locality"
},
  "geometry": {"coordinates":[38.73305,15.6897],"type":"Point"}
}