{
  "type": "Feature",
  "properties": {
    "gn:admin1_code":"02",
    "gn:asciiname":"Af May",
    "gn:country_code":"ER",
    "gn:dem":1932,
    "gn:feature_class":"P",
    "gn:feature_code":"PPL",
    "gn:name":"\u0100f May",
    "gn:population":0,
    "gn:timezone":"Africa/Asmara",
    "iso:country":"ER",
    "wof:name":"Af May",
    "wof:placetype":"locality"
},
  "geometry": {"coordinates":[38.80667,14.59694],"type":"Point"}
}