{
  "type": "Feature",
  "properties": {
    "gn:admin1_code":"00",
    "gn:asciiname":"Adi Geda",
    "gn:cc2":"ER",
    "gn:country_code":"ER",
    "gn:dem":1963,
    "gn:feature_class":"P",
    "gn:feature_code":"PPL",
    "gn:name":"\u0100d\u012b Geda",
    "gn:population":0,
    "gn:timezone":"Africa/Asmara",
    "iso:country":"ER",
    "name:und_x_variant":[
        "\u0100d\u012b Geda (1)",
        "\u0100d\u012b Geda"
    ],
    "wof:name":"Adi Geda",
    "wof:placetype":"locality"
},
  "geometry": {"coordinates":[38.80667,15.10139],"type":"Point"}
}