{
  "type": "Feature",
  "properties": {
    "gn:admin1_code":"05",
    "gn:asciiname":"Saladaro",
    "gn:country_code":"ER",
    "gn:dem":2291,
    "gn:feature_class":"P",
    "gn:feature_code":"PPL",
    "gn:name":"Saladaro",
    "gn:population":0,
    "gn:timezone":"Africa/Asmara",
    "iso:country":"ER",
    "name:und_x_variant":[
        "Sela\u2019i Da\u2019iro"
    ],
    "wof:name":"Saladaro",
    "wof:placetype":"locality"
},
  "geometry": {"coordinates":[38.87583,15.20528],"type":"Point"}
}