{
  "type": "Feature",
  "properties": {
    "gn:admin1_code":"05",
    "gn:asciiname":"Khamesi",
    "gn:country_code":"ER",
    "gn:dem":2314,
    "gn:feature_class":"P",
    "gn:feature_code":"PPL",
    "gn:name":"Khamesi",
    "gn:population":0,
    "gn:timezone":"Africa/Asmara",
    "iso:country":"ER",
    "wof:name":"Khamesi",
    "wof:placetype":"locality"
},
  "geometry": {"coordinates":[38.86239000000001,15.43163],"type":"Point"}
}