{
  "type": "Feature",
  "properties": {
    "gn:admin1_code":"01",
    "gn:asciiname":"Curoh",
    "gn:country_code":"ER",
    "gn:dem":1500,
    "gn:feature_class":"P",
    "gn:feature_code":"PPL",
    "gn:name":"Curoh",
    "gn:population":0,
    "gn:timezone":"Africa/Asmara",
    "iso:country":"ER",
    "name:und_x_variant":[
        "Kuro",
        "Kurokh"
    ],
    "wof:name":"Curoh",
    "wof:placetype":"locality"
},
  "geometry": {"coordinates":[38.77608,15.72196],"type":"Point"}
}