{
  "type": "Feature",
  "properties": {
    "gn:admin1_code":"06",
    "gn:asciiname":"Badn",
    "gn:country_code":"ER",
    "gn:dem":525,
    "gn:feature_class":"P",
    "gn:feature_code":"PPL",
    "gn:name":"Badn",
    "gn:population":0,
    "gn:timezone":"Africa/Asmara",
    "iso:country":"ER",
    "name:und_x_variant":[
        "Baden"
    ],
    "wof:name":"Badn",
    "wof:placetype":"locality"
},
  "geometry": {"coordinates":[37.96936,16.92546],"type":"Point"}
}