{
  "type": "Feature",
  "properties": {
    "gn:admin1_code":"02",
    "gn:asciiname":"Dub Dubaria",
    "gn:country_code":"ER",
    "gn:dem":1273,
    "gn:feature_class":"P",
    "gn:feature_code":"PPL",
    "gn:name":"Dub Dubaria",
    "gn:population":0,
    "gn:timezone":"Africa/Asmara",
    "iso:country":"ER",
    "name:und_x_variant":[
        "Rub Rubia",
        "Rub Rubiya",
        "Dub Dubaria"
    ],
    "wof:name":"Dub Dubaria",
    "wof:placetype":"locality"
},
  "geometry": {"coordinates":[39.18852,15.2173],"type":"Point"}
}