{
  "type": "Feature",
  "properties": {
    "gn:admin1_code":"06",
    "gn:asciiname":"Byra",
    "gn:country_code":"ER",
    "gn:dem":1120,
    "gn:feature_class":"P",
    "gn:feature_code":"PPL",
    "gn:name":"Byra",
    "gn:population":0,
    "gn:timezone":"Africa/Asmara",
    "iso:country":"ER",
    "wof:name":"Byra",
    "wof:placetype":"locality"
},
  "geometry": {"coordinates":[39.55598,15.09783],"type":"Point"}
}