{
  "type": "Feature",
  "properties": {
    "gn:admin1_code":"00",
    "gn:asciiname":"Keshe'at",
    "gn:country_code":"ER",
    "gn:dem":2213,
    "gn:feature_class":"P",
    "gn:feature_code":"PPL",
    "gn:name":"Keshe\u2019at",
    "gn:population":0,
    "gn:timezone":"Africa/Asmara",
    "iso:country":"ER",
    "wof:name":"Keshe'at",
    "wof:placetype":"locality"
},
  "geometry": {"coordinates":[39.37639,14.73139],"type":"Point"}
}