{
  "type": "Feature",
  "properties": {
    "gn:admin1_code":"02",
    "gn:asciiname":"Halibo",
    "gn:country_code":"ER",
    "gn:dem":1978,
    "gn:feature_class":"P",
    "gn:feature_code":"PPL",
    "gn:name":"Halibo",
    "gn:population":0,
    "gn:timezone":"Africa/Asmara",
    "iso:country":"ER",
    "name:und_x_variant":[
        "Khalibo",
        "Halibo"
    ],
    "wof:name":"Halibo",
    "wof:placetype":"locality"
},
  "geometry": {"coordinates":[39.08361,14.96861],"type":"Point"}
}