{
  "type": "Feature",
  "properties": {
    "gn:admin1_code":"03",
    "gn:asciiname":"Assa Ela",
    "gn:country_code":"ER",
    "gn:dem":4,
    "gn:feature_class":"P",
    "gn:feature_code":"PPL",
    "gn:name":"Assa Ela",
    "gn:population":0,
    "gn:timezone":"Africa/Asmara",
    "iso:country":"ER",
    "wof:name":"Assa Ela",
    "wof:placetype":"locality"
},
  "geometry": {"coordinates":[41.54904000000001,14.12778],"type":"Point"}
}