{
  "type": "Feature",
  "properties": {
    "gn:admin1_code":"03",
    "gn:asciiname":"Ad Gaban",
    "gn:country_code":"ER",
    "gn:dem":59,
    "gn:feature_class":"P",
    "gn:feature_code":"PPL",
    "gn:name":"Ad Gaban",
    "gn:population":0,
    "gn:timezone":"Africa/Asmara",
    "iso:country":"ER",
    "wof:name":"Ad Gaban",
    "wof:placetype":"locality"
},
  "geometry": {"coordinates":[40.88333,14.61667],"type":"Point"}
}