{
  "type": "Feature",
  "properties": {
    "gn:admin1_code":"02",
    "gn:asciiname":"Semanit",
    "gn:country_code":"ER",
    "gn:dem":1740,
    "gn:feature_class":"P",
    "gn:feature_code":"PPL",
    "gn:name":"Semanit",
    "gn:population":0,
    "gn:timezone":"Africa/Asmara",
    "iso:country":"ER",
    "wof:name":"Semanit",
    "wof:placetype":"locality"
},
  "geometry": {"coordinates":[39.03799,15.17016],"type":"Point"}
}