{
  "type": "Feature",
  "properties": {
    "gn:admin1_code":"03",
    "gn:asciiname":"Ferer",
    "gn:country_code":"ER",
    "gn:dem":547,
    "gn:feature_class":"P",
    "gn:feature_code":"PPL",
    "gn:name":"Ferer",
    "gn:population":0,
    "gn:timezone":"Africa/Asmara",
    "iso:country":"ER",
    "name:und_x_variant":[
        "Farar"
    ],
    "wof:name":"Ferer",
    "wof:placetype":"locality"
},
  "geometry": {"coordinates":[41.20226,13.76762],"type":"Point"}
}