{
  "type": "Feature",
  "properties": {
    "gn:admin1_code":"03",
    "gn:asciiname":"Saline",
    "gn:country_code":"ER",
    "gn:dem":9,
    "gn:feature_class":"P",
    "gn:feature_code":"PPL",
    "gn:name":"Saline",
    "gn:population":0,
    "gn:timezone":"Africa/Asmara",
    "iso:country":"ER",
    "name:bre_x_preferred":[
        "Saline"
    ],
    "name:ceb_x_preferred":[
        "Saline"
    ],
    "name:deu_x_preferred":[
        "Saline"
    ],
    "name:fra_x_preferred":[
        "Saline"
    ],
    "name:ita_x_preferred":[
        "Saline"
    ],
    "name:nld_x_preferred":[
        "Saline"
    ],
    "name:pol_x_preferred":[
        "Saline"
    ],
    "name:por_x_preferred":[
        "Saline"
    ],
    "name:spa_x_preferred":[
        "Saline"
    ],
    "name:srp_x_preferred":[
        "Saline"
    ],
    "name:swe_x_preferred":[
        "Saline"
    ],
    "name:vol_x_preferred":[
        "Saline"
    ],
    "wof:name":"Saline",
    "wof:placetype":"locality"
},
  "geometry": {"coordinates":[42.30353,13.48881],"type":"Point"}
}