{
  "type": "Feature",
  "properties": {
    "gn:admin1_code":"00",
    "gn:asciiname":"Moroho",
    "gn:country_code":"ER",
    "gn:dem":1352,
    "gn:feature_class":"P",
    "gn:feature_code":"PPL",
    "gn:name":"Moroho",
    "gn:population":0,
    "gn:timezone":"Africa/Asmara",
    "iso:country":"ER",
    "name:und_x_variant":[
        "Morokho",
        "Moroho"
    ],
    "wof:name":"Moroho",
    "wof:placetype":"locality"
},
  "geometry": {"coordinates":[38.39944000000001,14.5425],"type":"Point"}
}