{
  "type": "Feature",
  "properties": {
    "gn:admin1_code":"01",
    "gn:asciiname":"Derkano",
    "gn:country_code":"ER",
    "gn:dem":1682,
    "gn:feature_class":"P",
    "gn:feature_code":"PPL",
    "gn:name":"Derkano",
    "gn:population":0,
    "gn:timezone":"Africa/Asmara",
    "iso:country":"ER",
    "wof:name":"Derkano",
    "wof:placetype":"locality"
},
  "geometry": {"coordinates":[38.46991,15.67233],"type":"Point"}
}