{
  "type": "Feature",
  "properties": {
    "gn:admin1_code":"06",
    "gn:asciiname":"Bizione",
    "gn:country_code":"ER",
    "gn:dem":2422,
    "gn:feature_class":"P",
    "gn:feature_code":"PPL",
    "gn:name":"Bizione",
    "gn:population":0,
    "gn:timezone":"Africa/Asmara",
    "iso:country":"ER",
    "name:und_x_variant":[
        "B\u012bzen",
        "Bizione"
    ],
    "wof:name":"Bizione",
    "wof:placetype":"locality"
},
  "geometry": {"coordinates":[39.08527,15.32895],"type":"Point"}
}