{
  "type": "Feature",
  "properties": {
    "gn:admin1_code":"00",
    "gn:asciiname":"Halay",
    "gn:country_code":"ER",
    "gn:dem":2579,
    "gn:feature_class":"P",
    "gn:feature_code":"PPL",
    "gn:name":"Halay",
    "gn:population":0,
    "gn:timezone":"Africa/Asmara",
    "iso:country":"ER",
    "name:und_x_variant":[
        "Khalay",
        "Halay"
    ],
    "wof:name":"Halay",
    "wof:placetype":"locality"
},
  "geometry": {"coordinates":[39.3275,14.99778],"type":"Point"}
}