{
  "type": "Feature",
  "properties": {
    "gn:admin1_code":"00",
    "gn:asciiname":"Vann",
    "gn:country_code":"ER",
    "gn:dem":315,
    "gn:feature_class":"P",
    "gn:feature_code":"PPL",
    "gn:name":"Vann",
    "gn:population":0,
    "gn:timezone":"Africa/Asmara",
    "iso:country":"ER",
    "wof:name":"Vann",
    "wof:placetype":"locality"
},
  "geometry": {"coordinates":[42.63333,12.65],"type":"Point"}
}