{
  "type": "Feature",
  "properties": {
    "gn:admin1_code":"06",
    "gn:asciiname":"Sebar Guma",
    "gn:country_code":"ER",
    "gn:dem":380,
    "gn:feature_class":"P",
    "gn:feature_code":"PPL",
    "gn:name":"Sebar Guma",
    "gn:population":0,
    "gn:timezone":"Africa/Asmara",
    "iso:country":"ER",
    "name:und_x_variant":[
        "Sabarguma"
    ],
    "wof:name":"Sebar Guma",
    "wof:placetype":"locality"
},
  "geometry": {"coordinates":[39.12574,15.49364],"type":"Point"}
}