{
  "type": "Feature",
  "properties": {
    "gn:admin1_code":"06",
    "gn:asciiname":"Ona",
    "gn:country_code":"ER",
    "gn:dem":1380,
    "gn:feature_class":"P",
    "gn:feature_code":"PPL",
    "gn:name":"Ona",
    "gn:population":0,
    "gn:timezone":"Africa/Asmara",
    "iso:country":"ER",
    "name:bre_x_preferred":[
        "Ona"
    ],
    "name:cat_x_preferred":[
        "Ona"
    ],
    "name:ceb_x_preferred":[
        "Ona"
    ],
    "name:ces_x_preferred":[
        "Ona"
    ],
    "name:fra_x_preferred":[
        "Ona"
    ],
    "name:lit_x_preferred":[
        "Ona"
    ],
    "name:nld_x_preferred":[
        "Ona"
    ],
    "name:nor_x_preferred":[
        "Ona"
    ],
    "name:spa_x_preferred":[
        "Ona"
    ],
    "wof:name":"Ona",
    "wof:placetype":"locality"
},
  "geometry": {"coordinates":[38.45962,15.79669],"type":"Point"}
}