{
  "type": "Feature",
  "properties": {
    "gn:admin1_code":"06",
    "gn:asciiname":"Angaba",
    "gn:country_code":"ER",
    "gn:dem":1170,
    "gn:feature_class":"P",
    "gn:feature_code":"PPL",
    "gn:name":"Angaba",
    "gn:population":0,
    "gn:timezone":"Africa/Asmara",
    "iso:country":"ER",
    "wof:name":"Angaba",
    "wof:placetype":"locality"
},
  "geometry": {"coordinates":[38.56064,16.53659],"type":"Point"}
}