{
  "type": "Feature",
  "properties": {
    "gn:admin1_code":"04",
    "gn:asciiname":"Omhajer",
    "gn:country_code":"ER",
    "gn:dem":595,
    "gn:feature_class":"P",
    "gn:feature_code":"PPL",
    "gn:name":"Omh\u0101jer",
    "gn:population":0,
    "gn:timezone":"Africa/Asmara",
    "iso:country":"ER",
    "name:pol_x_preferred":[
        "Om Hajer"
    ],
    "name:und_x_variant":[
        "Om Hager",
        "Minhajer",
        "Om Hayer",
        "Om Ager",
        "Umm Hagar",
        "Minkhadzher",
        "Omh\u0101jer"
    ],
    "wof:name":"Omhajer",
    "wof:placetype":"locality"
},
  "geometry": {"coordinates":[36.64437,14.32761],"type":"Point"}
}