{
  "type": "Feature",
  "properties": {
    "gn:admin1_code":"06",
    "gn:asciiname":"Mefalk",
    "gn:country_code":"ER",
    "gn:dem":1146,
    "gn:feature_class":"P",
    "gn:feature_code":"PPL",
    "gn:name":"Mefalk",
    "gn:population":0,
    "gn:timezone":"Africa/Asmara",
    "iso:country":"ER",
    "wof:name":"Mefalk",
    "wof:placetype":"locality"
},
  "geometry": {"coordinates":[38.68339,15.93999],"type":"Point"}
}