{
  "type": "Feature",
  "properties": {
    "gn:admin1_code":"06",
    "gn:asciiname":"Etharawyatat",
    "gn:country_code":"ER",
    "gn:dem":1567,
    "gn:feature_class":"P",
    "gn:feature_code":"PPL",
    "gn:name":"Etharawyatat",
    "gn:population":0,
    "gn:timezone":"Africa/Asmara",
    "iso:country":"ER",
    "wof:name":"Etharawyatat",
    "wof:placetype":"locality"
},
  "geometry": {"coordinates":[38.33279,16.23416],"type":"Point"}
}