{
  "type": "Feature",
  "properties": {
    "gn:admin1_code":"06",
    "gn:asciiname":"Mrara",
    "gn:country_code":"ER",
    "gn:dem":1909,
    "gn:feature_class":"P",
    "gn:feature_code":"PPL",
    "gn:name":"Mrara",
    "gn:population":0,
    "gn:timezone":"Africa/Asmara",
    "iso:country":"ER",
    "wof:name":"Mrara",
    "wof:placetype":"locality"
},
  "geometry": {"coordinates":[38.87462,15.68914],"type":"Point"}
}