{
  "type": "Feature",
  "properties": {
    "gn:admin1_code":"04",
    "gn:asciiname":"Adi-Ne'amn",
    "gn:country_code":"ER",
    "gn:dem":1839,
    "gn:feature_class":"P",
    "gn:feature_code":"PPL",
    "gn:name":"\u0100d\u012b-Ne\u2019amn",
    "gn:population":0,
    "gn:timezone":"Africa/Asmara",
    "iso:country":"ER",
    "name:und_x_variant":[
        "Adi Naamen",
        "\u0100d\u012b-Ne\u2019amn"
    ],
    "wof:name":"Adi-Ne'amn",
    "wof:placetype":"locality"
},
  "geometry": {"coordinates":[38.69201,15.49148],"type":"Point"}
}