{
  "type": "Feature",
  "properties": {
    "gn:admin1_code":"00",
    "gn:asciiname":"Keman Koba",
    "gn:country_code":"ER",
    "gn:dem":1700,
    "gn:feature_class":"P",
    "gn:feature_code":"PPL",
    "gn:name":"Keman Koba",
    "gn:population":0,
    "gn:timezone":"Africa/Asmara",
    "iso:country":"ER",
    "wof:name":"Keman Koba",
    "wof:placetype":"locality"
},
  "geometry": {"coordinates":[38.30111,14.95528],"type":"Point"}
}