{
  "type": "Feature",
  "properties": {
    "gn:admin1_code":"05",
    "gn:asciiname":"Addi Kares",
    "gn:country_code":"ER",
    "gn:dem":2112,
    "gn:feature_class":"P",
    "gn:feature_code":"PPL",
    "gn:name":"Addi Kares",
    "gn:population":0,
    "gn:timezone":"Africa/Asmara",
    "iso:country":"ER",
    "wof:name":"Addi Kares",
    "wof:placetype":"locality"
},
  "geometry": {"coordinates":[38.9371,15.12776],"type":"Point"}
}