{
  "type": "Feature",
  "properties": {
    "gn:admin1_code":"01",
    "gn:asciiname":"Debalk'o",
    "gn:country_code":"ER",
    "gn:dem":1703,
    "gn:feature_class":"P",
    "gn:feature_code":"PPL",
    "gn:name":"Debalk\u2019o",
    "gn:population":0,
    "gn:timezone":"Africa/Asmara",
    "iso:country":"ER",
    "wof:name":"Debalk'o",
    "wof:placetype":"locality"
},
  "geometry": {"coordinates":[38.64111,15.71194],"type":"Point"}
}