{
  "type": "Feature",
  "properties": {
    "gn:admin1_code":"00",
    "gn:asciiname":"Adi-W'ala",
    "gn:country_code":"ER",
    "gn:dem":1645,
    "gn:feature_class":"P",
    "gn:feature_code":"PPL",
    "gn:name":"Adi-W\u2019ala",
    "gn:population":0,
    "gn:timezone":"Africa/Asmara",
    "iso:country":"ER",
    "name:und_x_variant":[
        "Addi-Uala",
        "Adi-W\u2019ala"
    ],
    "wof:name":"Adi-W'ala",
    "wof:placetype":"locality"
},
  "geometry": {"coordinates":[38.38167,14.82389],"type":"Point"}
}