{
  "type": "Feature",
  "properties": {
    "gn:admin1_code":"02",
    "gn:asciiname":"Ghile'e La'elay",
    "gn:country_code":"ER",
    "gn:dem":1854,
    "gn:feature_class":"P",
    "gn:feature_code":"PPL",
    "gn:name":"Ghile\u2019e La\u2019elay",
    "gn:population":0,
    "gn:timezone":"Africa/Asmara",
    "iso:country":"ER",
    "wof:name":"Ghile'e La'elay",
    "wof:placetype":"locality"
},
  "geometry": {"coordinates":[38.20063,17.4978],"type":"Point"}
}