{
  "type": "Feature",
  "properties": {
    "gn:admin1_code":"04",
    "gn:asciiname":"Fafaro",
    "gn:country_code":"ER",
    "gn:dem":911,
    "gn:feature_class":"P",
    "gn:feature_code":"PPL",
    "gn:name":"Fafaro",
    "gn:population":0,
    "gn:timezone":"Africa/Asmara",
    "iso:country":"ER",
    "wof:name":"Fafaro",
    "wof:placetype":"locality"
},
  "geometry": {"coordinates":[37.7725,14.95889],"type":"Point"}
}