{
  "type": "Feature",
  "properties": {
    "gn:admin1_code":"02",
    "gn:asciiname":"Cudo Hoiva",
    "gn:country_code":"ER",
    "gn:dem":1620,
    "gn:feature_class":"P",
    "gn:feature_code":"PPL",
    "gn:name":"Cudo Hoiva",
    "gn:population":0,
    "gn:timezone":"Africa/Asmara",
    "iso:country":"ER",
    "name:und_x_variant":[
        "Kudo Khoysa",
        "Cudo Hoiva"
    ],
    "wof:name":"Cudo Hoiva",
    "wof:placetype":"locality"
},
  "geometry": {"coordinates":[39.18583,14.60333],"type":"Point"}
}