{
  "type": "Feature",
  "properties": {
    "gn:admin1_code":"01",
    "gn:asciiname":"Halib-Mentel",
    "gn:country_code":"ER",
    "gn:dem":1444,
    "gn:feature_class":"P",
    "gn:feature_code":"PPL",
    "gn:name":"Hal\u012bb-Mentel",
    "gn:population":0,
    "gn:timezone":"Africa/Asmara",
    "iso:country":"ER",
    "name:und_x_variant":[
        "Hadis",
        "Habi Mantel",
        "Hal\u012bb-Mentel"
    ],
    "wof:name":"Halib-Mentel",
    "wof:placetype":"locality"
},
  "geometry": {"coordinates":[38.54716,15.74261],"type":"Point"}
}