{
  "type": "Feature",
  "properties": {
    "gn:admin1_code":"02",
    "gn:asciiname":"Adi Aba Ri'isom",
    "gn:country_code":"ER",
    "gn:dem":1515,
    "gn:feature_class":"P",
    "gn:feature_code":"PPL",
    "gn:name":"\u0100d\u012b \u0100ba Ri\u2019isom",
    "gn:population":0,
    "gn:timezone":"Africa/Asmara",
    "iso:country":"ER",
    "name:und_x_variant":[
        "Addi Abba Riisom",
        "\u0100d\u012b \u0100ba Ri\u2019isom"
    ],
    "wof:name":"Adi Aba Ri'isom",
    "wof:placetype":"locality"
},
  "geometry": {"coordinates":[38.72306,14.55],"type":"Point"}
}