{
  "type": "Feature",
  "properties": {
    "gn:admin1_code":"02",
    "gn:asciiname":"Una-Andom",
    "gn:country_code":"ER",
    "gn:dem":1694,
    "gn:feature_class":"P",
    "gn:feature_code":"PPL",
    "gn:name":"Una-Andom",
    "gn:population":0,
    "gn:timezone":"Africa/Asmara",
    "iso:country":"ER",
    "name:und_x_variant":[
        "Ona Andom",
        "Una-Andom"
    ],
    "wof:name":"Una-Andom",
    "wof:placetype":"locality"
},
  "geometry": {"coordinates":[39.21861,14.75417],"type":"Point"}
}