{
  "type": "Feature",
  "properties": {
    "gn:admin1_code":"04",
    "gn:asciiname":"Dedda Baza",
    "gn:country_code":"ER",
    "gn:dem":1085,
    "gn:feature_class":"P",
    "gn:feature_code":"PPL",
    "gn:name":"Dedda Baza",
    "gn:population":0,
    "gn:timezone":"Africa/Asmara",
    "iso:country":"ER",
    "wof:name":"Dedda Baza",
    "wof:placetype":"locality"
},
  "geometry": {"coordinates":[37.71061,15.23785],"type":"Point"}
}