{
  "type": "Feature",
  "properties": {
    "gn:admin1_code":"00",
    "gn:asciiname":"Kesa-Kalati",
    "gn:country_code":"ER",
    "gn:dem":1702,
    "gn:feature_class":"P",
    "gn:feature_code":"PPL",
    "gn:name":"Kesa-Kalati",
    "gn:population":0,
    "gn:timezone":"Africa/Asmara",
    "iso:country":"ER",
    "wof:name":"Kesa-Kalati",
    "wof:placetype":"locality"
},
  "geometry": {"coordinates":[38.46505,15.02461],"type":"Point"}
}