{
  "type": "Feature",
  "properties": {
    "gn:admin1_code":"02",
    "gn:asciiname":"Berakit-Abay",
    "gn:country_code":"ER",
    "gn:dem":1912,
    "gn:feature_class":"P",
    "gn:feature_code":"PPL",
    "gn:name":"Berakit-Abay",
    "gn:population":0,
    "gn:timezone":"Africa/Asmara",
    "iso:country":"ER",
    "name:und_x_variant":[
        "Barakit",
        "Berakit-Abay"
    ],
    "wof:name":"Berakit-Abay",
    "wof:placetype":"locality"
},
  "geometry": {"coordinates":[39.17056,14.955],"type":"Point"}
}