{
  "type": "Feature",
  "properties": {
    "gn:admin1_code":"02",
    "gn:asciiname":"Hantsetse",
    "gn:country_code":"ER",
    "gn:dem":1835,
    "gn:feature_class":"P",
    "gn:feature_code":"PPL",
    "gn:name":"Hantsetse",
    "gn:population":0,
    "gn:timezone":"Africa/Asmara",
    "iso:country":"ER",
    "name:und_x_variant":[
        "Khantsetse",
        "Hantsetse"
    ],
    "wof:name":"Hantsetse",
    "wof:placetype":"locality"
},
  "geometry": {"coordinates":[38.59556,14.72556],"type":"Point"}
}