{
  "type": "Feature",
  "properties": {
    "gn:admin1_code":"02",
    "gn:asciiname":"Adilges",
    "gn:country_code":"ER",
    "gn:dem":1924,
    "gn:feature_class":"P",
    "gn:feature_code":"PPL",
    "gn:name":"\u0100dilges",
    "gn:population":0,
    "gn:timezone":"Africa/Asmara",
    "iso:country":"ER",
    "name:rus_x_preferred":[
        "Adi Al\u2019ges"
    ],
    "name:und_x_variant":[
        "\u0100dilges"
    ],
    "wof:name":"Adilges",
    "wof:placetype":"locality"
},
  "geometry": {"coordinates":[38.84722,14.6725],"type":"Point"}
}