{
  "type": "Feature",
  "properties": {
    "gn:admin1_code":"06",
    "gn:asciiname":"Gher",
    "gn:country_code":"ER",
    "gn:dem":1020,
    "gn:feature_class":"P",
    "gn:feature_code":"PPL",
    "gn:name":"Gher",
    "gn:population":0,
    "gn:timezone":"Africa/Asmara",
    "iso:country":"ER",
    "wof:name":"Gher",
    "wof:placetype":"locality"
},
  "geometry": {"coordinates":[38.29084,16.16212],"type":"Point"}
}