{
  "type": "Feature",
  "properties": {
    "gn:admin1_code":"06",
    "gn:asciiname":"Agokha",
    "gn:country_code":"ER",
    "gn:dem":1673,
    "gn:feature_class":"P",
    "gn:feature_code":"PPL",
    "gn:name":"Agokha",
    "gn:population":0,
    "gn:timezone":"Africa/Asmara",
    "iso:country":"ER",
    "wof:name":"Agokha",
    "wof:placetype":"locality"
},
  "geometry": {"coordinates":[39.4056,15.07874],"type":"Point"}
}