{
  "type": "Feature",
  "properties": {
    "gn:admin1_code":"06",
    "gn:asciiname":"Cheweni",
    "gn:country_code":"ER",
    "gn:dem":1275,
    "gn:feature_class":"P",
    "gn:feature_code":"PPL",
    "gn:name":"Cheweni",
    "gn:population":0,
    "gn:timezone":"Africa/Asmara",
    "iso:country":"ER",
    "wof:name":"Cheweni",
    "wof:placetype":"locality"
},
  "geometry": {"coordinates":[38.40503,16.24365],"type":"Point"}
}