{
  "type": "Feature",
  "properties": {
    "gn:admin1_code":"06",
    "gn:asciiname":"Scillichi",
    "gn:country_code":"ER",
    "gn:dem":111,
    "gn:feature_class":"P",
    "gn:feature_code":"PPL",
    "gn:name":"Scillichi",
    "gn:population":0,
    "gn:timezone":"Africa/Asmara",
    "iso:country":"ER",
    "name:ita_x_preferred":[
        "Scillichi"
    ],
    "wof:name":"Scillichi",
    "wof:placetype":"locality"
},
  "geometry": {"coordinates":[39.48918,15.40501],"type":"Point"}
}