{
  "type": "Feature",
  "properties": {
    "gn:admin1_code":"02",
    "gn:asciiname":"Tukul' Omar",
    "gn:country_code":"ER",
    "gn:dem":1563,
    "gn:feature_class":"P",
    "gn:feature_code":"PPL",
    "gn:name":"Tukul\u2019 Omar",
    "gn:population":0,
    "gn:timezone":"Africa/Asmara",
    "iso:country":"ER",
    "name:rus_x_preferred":[
        "Tukul\u2019 Omar"
    ],
    "wof:name":"Tukul' Omar",
    "wof:placetype":"locality"
},
  "geometry": {"coordinates":[39.34362,15.067],"type":"Point"}
}