{
  "type": "Feature",
  "properties": {
    "gn:admin1_code":"05",
    "gn:asciiname":"Beleza",
    "gn:country_code":"ER",
    "gn:dem":2428,
    "gn:feature_class":"P",
    "gn:feature_code":"PPL",
    "gn:name":"Beleza",
    "gn:population":0,
    "gn:timezone":"Africa/Asmara",
    "iso:country":"ER",
    "name:und_x_variant":[
        "Belesa",
        "Beleza"
    ],
    "wof:name":"Beleza",
    "wof:placetype":"locality"
},
  "geometry": {"coordinates":[38.92549,15.42551],"type":"Point"}
}