{
  "type": "Feature",
  "properties": {
    "gn:admin1_code":"02",
    "gn:asciiname":"Ho Ho",
    "gn:country_code":"ER",
    "gn:dem":1664,
    "gn:feature_class":"P",
    "gn:feature_code":"PPL",
    "gn:name":"Ho Ho",
    "gn:population":0,
    "gn:timezone":"Africa/Asmara",
    "iso:country":"ER",
    "name:und_x_variant":[
        "Kho Kho",
        "Ho Ho"
    ],
    "wof:name":"Ho Ho",
    "wof:placetype":"locality"
},
  "geometry": {"coordinates":[38.94028,14.77639],"type":"Point"}
}