{
  "type": "Feature",
  "properties": {
    "gn:admin1_code":"06",
    "gn:asciiname":"Ad Issa",
    "gn:country_code":"ER",
    "gn:dem":788,
    "gn:feature_class":"P",
    "gn:feature_code":"PPL",
    "gn:name":"Ad Issa",
    "gn:population":0,
    "gn:timezone":"Africa/Asmara",
    "iso:country":"ER",
    "wof:name":"Ad Issa",
    "wof:placetype":"locality"
},
  "geometry": {"coordinates":[38.2041,15.66614],"type":"Point"}
}