{
  "type": "Feature",
  "properties": {
    "gn:admin1_code":"06",
    "gn:asciiname":"Ascidira",
    "gn:country_code":"ER",
    "gn:dem":1054,
    "gn:feature_class":"P",
    "gn:feature_code":"PPL",
    "gn:name":"Ascidira",
    "gn:population":0,
    "gn:timezone":"Africa/Asmara",
    "iso:country":"ER",
    "name:und_x_variant":[
        "Asciadira",
        "Ascidira"
    ],
    "wof:name":"Ascidira",
    "wof:placetype":"locality"
},
  "geometry": {"coordinates":[38.3943,15.75089],"type":"Point"}
}