{
  "type": "Feature",
  "properties": {
    "gn:admin1_code":"01",
    "gn:asciiname":"Selaba She'ib",
    "gn:country_code":"ER",
    "gn:dem":2095,
    "gn:feature_class":"P",
    "gn:feature_code":"PPL",
    "gn:name":"Selaba She\u2019\u012bb",
    "gn:population":0,
    "gn:timezone":"Africa/Asmara",
    "iso:country":"ER",
    "name:und_x_variant":[
        "Seleba She\u2019\u012bb",
        "Rapto",
        "Selaba She\u2019\u012bb"
    ],
    "wof:name":"Selaba She'ib",
    "wof:placetype":"locality"
},
  "geometry": {"coordinates":[38.6686,15.74478],"type":"Point"}
}