{
  "type": "Feature",
  "properties": {
    "gn:admin1_code":"00",
    "gn:asciiname":"Magala",
    "gn:country_code":"ER",
    "gn:dem":824,
    "gn:feature_class":"P",
    "gn:feature_code":"PPL",
    "gn:name":"Magala",
    "gn:population":0,
    "gn:timezone":"Africa/Asmara",
    "iso:country":"ER",
    "wof:name":"Magala",
    "wof:placetype":"locality"
},
  "geometry": {"coordinates":[36.91778,14.555],"type":"Point"}
}