{
  "type": "Feature",
  "properties": {
    "gn:admin1_code":"04",
    "gn:asciiname":"Ad-Maad",
    "gn:country_code":"ER",
    "gn:dem":674,
    "gn:feature_class":"P",
    "gn:feature_code":"PPL",
    "gn:name":"Ad-Maad",
    "gn:population":0,
    "gn:timezone":"Africa/Asmara",
    "iso:country":"ER",
    "wof:name":"Ad-Maad",
    "wof:placetype":"locality"
},
  "geometry": {"coordinates":[37.40293,15.30589],"type":"Point"}
}