{
  "type": "Feature",
  "properties": {
    "gn:admin1_code":"02",
    "gn:asciiname":"Adi Scimandui",
    "gn:country_code":"ER",
    "gn:dem":2083,
    "gn:feature_class":"P",
    "gn:feature_code":"PPL",
    "gn:name":"Adi Scimandui",
    "gn:population":0,
    "gn:timezone":"Africa/Asmara",
    "iso:country":"ER",
    "name:und_x_variant":[
        "Adi Shunandvi",
        "Adi Scimandui"
    ],
    "wof:name":"Adi Scimandui",
    "wof:placetype":"locality"
},
  "geometry": {"coordinates":[38.72833,14.95722],"type":"Point"}
}