{
  "type": "Feature",
  "properties": {
    "gn:admin1_code":"05",
    "gn:asciiname":"Adi Gebray",
    "gn:country_code":"ER",
    "gn:dem":2281,
    "gn:feature_class":"P",
    "gn:feature_code":"PPL",
    "gn:name":"\u0100d\u012b Gebray",
    "gn:population":0,
    "gn:timezone":"Africa/Asmara",
    "iso:country":"ER",
    "name:und_x_variant":[
        "Grar Gabru",
        "\u0100d\u012b Gebray"
    ],
    "wof:name":"Adi Gebray",
    "wof:placetype":"locality"
},
  "geometry": {"coordinates":[38.7364,15.21144],"type":"Point"}
}