{
  "type": "Feature",
  "properties": {
    "gn:admin1_code":"02",
    "gn:asciiname":"Adi Tesfa Leul",
    "gn:country_code":"ER",
    "gn:dem":1954,
    "gn:feature_class":"P",
    "gn:feature_code":"PPL",
    "gn:name":"Adi Tesfa Leul",
    "gn:population":0,
    "gn:timezone":"Africa/Asmara",
    "iso:country":"ER",
    "wof:name":"Adi Tesfa Leul",
    "wof:placetype":"locality"
},
  "geometry": {"coordinates":[38.52667,14.73778],"type":"Point"}
}