{
  "type": "Feature",
  "properties": {
    "gn:admin1_code":"03",
    "gn:asciiname":"Mergebla",
    "gn:country_code":"ER",
    "gn:dem":8,
    "gn:feature_class":"P",
    "gn:feature_code":"PPL",
    "gn:name":"M\u0113rg\u0113bla",
    "gn:population":0,
    "gn:timezone":"Africa/Asmara",
    "iso:country":"ER",
    "name:und_x_variant":[
        "Margable",
        "M\u0113rg\u0113bla"
    ],
    "wof:name":"Mergebla",
    "wof:placetype":"locality"
},
  "geometry": {"coordinates":[42.74415,12.90055],"type":"Point"}
}