{
  "type": "Feature",
  "properties": {
    "gn:admin1_code":"06",
    "gn:asciiname":"Et'andelet",
    "gn:country_code":"ER",
    "gn:dem":1329,
    "gn:feature_class":"P",
    "gn:feature_code":"PPL",
    "gn:name":"Et\u2019andelet",
    "gn:population":0,
    "gn:timezone":"Africa/Asmara",
    "iso:country":"ER",
    "wof:name":"Et'andelet",
    "wof:placetype":"locality"
},
  "geometry": {"coordinates":[38.41656,16.20363],"type":"Point"}
}