{
  "type": "Feature",
  "properties": {
    "gn:asciiname":"Gulomahda",
    "gn:country_code":"ER",
    "gn:dem":2184,
    "gn:feature_class":"P",
    "gn:feature_code":"PPL",
    "gn:name":"Gulomahda",
    "gn:population":0,
    "gn:timezone":"Africa/Asmara",
    "iso:country":"ER",
    "wof:name":"Gulomahda",
    "wof:placetype":"locality"
},
  "geometry": {"coordinates":[39.44,14.54],"type":"Point"}
}