{
  "type": "Feature",
  "properties": {
    "gn:admin1_code":"06",
    "gn:asciiname":"Ganga",
    "gn:country_code":"ER",
    "gn:dem":1368,
    "gn:feature_class":"P",
    "gn:feature_code":"PPL",
    "gn:name":"Ganga",
    "gn:population":0,
    "gn:timezone":"Africa/Asmara",
    "iso:country":"ER",
    "wof:name":"Ganga",
    "wof:placetype":"locality"
},
  "geometry": {"coordinates":[39.4075,15.18107],"type":"Point"}
}