{
  "type": "Feature",
  "properties": {
    "gn:admin1_code":"03",
    "gn:asciiname":"Babaiu",
    "gn:country_code":"ER",
    "gn:dem":0,
    "gn:feature_class":"P",
    "gn:feature_code":"PPL",
    "gn:name":"Babaiu",
    "gn:population":0,
    "gn:timezone":"Africa/Asmara",
    "iso:country":"ER",
    "name:und_x_variant":[
        "Babayu"
    ],
    "wof:name":"Babaiu",
    "wof:placetype":"locality"
},
  "geometry": {"coordinates":[41.22187,14.56127],"type":"Point"}
}