{
  "type": "Feature",
  "properties": {
    "gn:admin1_code":"03",
    "gn:asciiname":"Asbol",
    "gn:country_code":"ER",
    "gn:dem":180,
    "gn:feature_class":"P",
    "gn:feature_code":"PPL",
    "gn:name":"Asbol",
    "gn:population":0,
    "gn:timezone":"Africa/Asmara",
    "iso:country":"ER",
    "wof:name":"Asbol",
    "wof:placetype":"locality"
},
  "geometry": {"coordinates":[42.65312,12.71999],"type":"Point"}
}