{
  "type": "Feature",
  "properties": {
    "gn:admin1_code":"03",
    "gn:asciiname":"Gahare",
    "gn:country_code":"ER",
    "gn:dem":224,
    "gn:feature_class":"P",
    "gn:feature_code":"PPL",
    "gn:name":"Gahare",
    "gn:population":0,
    "gn:timezone":"Africa/Asmara",
    "iso:country":"ER",
    "name:und_x_variant":[
        "Gehar\u0113"
    ],
    "wof:name":"Gahare",
    "wof:placetype":"locality"
},
  "geometry": {"coordinates":[42.07248,13.23539],"type":"Point"}
}