{
  "type": "Feature",
  "properties": {
    "gn:admin1_code":"02",
    "gn:asciiname":"Adi Lamza",
    "gn:country_code":"ER",
    "gn:dem":2328,
    "gn:feature_class":"P",
    "gn:feature_code":"PPL",
    "gn:name":"\u0100d\u012b Lamza",
    "gn:population":0,
    "gn:timezone":"Africa/Asmara",
    "iso:country":"ER",
    "wof:name":"Adi Lamza",
    "wof:placetype":"locality"
},
  "geometry": {"coordinates":[38.89955,15.21633],"type":"Point"}
}