{
  "type": "Feature",
  "properties": {
    "gn:admin1_code":"06",
    "gn:asciiname":"Marke",
    "gn:country_code":"ER",
    "gn:dem":1828,
    "gn:feature_class":"P",
    "gn:feature_code":"PPL",
    "gn:name":"Marke",
    "gn:population":0,
    "gn:timezone":"Africa/Asmara",
    "iso:country":"ER",
    "name:als_x_preferred":[
        "Marke"
    ],
    "name:ceb_x_preferred":[
        "Marke"
    ],
    "name:deu_x_preferred":[
        "Marke"
    ],
    "name:fry_x_preferred":[
        "Marke"
    ],
    "name:lit_x_preferred":[
        "Mark\u0117"
    ],
    "name:nld_x_preferred":[
        "Marke"
    ],
    "name:pol_x_preferred":[
        "Marke"
    ],
    "name:rus_x_preferred":[
        "\u041c\u0430\u0440\u043a\u0435"
    ],
    "name:swe_x_preferred":[
        "Marke"
    ],
    "wof:name":"Marke",
    "wof:placetype":"locality"
},
  "geometry": {"coordinates":[38.2276,15.90072],"type":"Point"}
}