{
  "type": "Feature",
  "properties": {
    "gn:admin1_code":"02",
    "gn:asciiname":"Samassen",
    "gn:country_code":"ER",
    "gn:dem":2216,
    "gn:feature_class":"P",
    "gn:feature_code":"PPL",
    "gn:name":"Samassen",
    "gn:population":0,
    "gn:timezone":"Africa/Asmara",
    "iso:country":"ER",
    "wof:name":"Samassen",
    "wof:placetype":"locality"
},
  "geometry": {"coordinates":[38.72333,14.99278],"type":"Point"}
}