{
  "type": "Feature",
  "properties": {
    "gn:admin1_code":"04",
    "gn:asciiname":"Arnedda",
    "gn:country_code":"ER",
    "gn:dem":681,
    "gn:feature_class":"P",
    "gn:feature_code":"PPL",
    "gn:name":"Arnedda",
    "gn:population":0,
    "gn:timezone":"Africa/Asmara",
    "iso:country":"ER",
    "wof:name":"Arnedda",
    "wof:placetype":"locality"
},
  "geometry": {"coordinates":[37.56709,15.31038],"type":"Point"}
}