{
  "type": "Feature",
  "properties": {
    "gn:admin1_code":"06",
    "gn:asciiname":"Deset",
    "gn:country_code":"ER",
    "gn:dem":63,
    "gn:feature_class":"P",
    "gn:feature_code":"PPL",
    "gn:name":"Des\u0113t",
    "gn:population":0,
    "gn:timezone":"Africa/Asmara",
    "iso:country":"ER",
    "wof:name":"Deset",
    "wof:placetype":"locality"
},
  "geometry": {"coordinates":[39.3289,15.6606],"type":"Point"}
}