{
  "type": "Feature",
  "properties": {
    "gn:admin1_code":"00",
    "gn:asciiname":"Adi-Ketina",
    "gn:cc2":"ER",
    "gn:country_code":"ER",
    "gn:dem":1799,
    "gn:feature_class":"P",
    "gn:feature_code":"PPL",
    "gn:name":"Adi-Ketina",
    "gn:population":0,
    "gn:timezone":"Africa/Asmara",
    "iso:country":"ER",
    "name:und_x_variant":[
        "Adi Catina",
        "Adi-Ketina"
    ],
    "wof:name":"Adi-Ketina",
    "wof:placetype":"locality"
},
  "geometry": {"coordinates":[38.49861,14.53833],"type":"Point"}
}