{
  "type": "Feature",
  "properties": {
    "gn:admin1_code":"02",
    "gn:asciiname":"Ad Finne",
    "gn:country_code":"ER",
    "gn:dem":1820,
    "gn:feature_class":"P",
    "gn:feature_code":"PPL",
    "gn:name":"Ad Finne",
    "gn:population":0,
    "gn:timezone":"Africa/Asmara",
    "iso:country":"ER",
    "name:und_x_variant":[
        "Adi Finne",
        "Ad Finne"
    ],
    "wof:name":"Ad Finne",
    "wof:placetype":"locality"
},
  "geometry": {"coordinates":[38.93333,14.94806],"type":"Point"}
}