{
  "type": "Feature",
  "properties": {
    "gn:admin1_code":"04",
    "gn:asciiname":"Mare",
    "gn:country_code":"ER",
    "gn:dem":1971,
    "gn:feature_class":"P",
    "gn:feature_code":"PPL",
    "gn:name":"Mare",
    "gn:population":0,
    "gn:timezone":"Africa/Asmara",
    "iso:country":"ER",
    "wof:name":"Mare",
    "wof:placetype":"locality"
},
  "geometry": {"coordinates":[38.63517,15.22914],"type":"Point"}
}