{
  "type": "Feature",
  "properties": {
    "gn:admin1_code":"04",
    "gn:asciiname":"Armara",
    "gn:country_code":"ER",
    "gn:dem":857,
    "gn:feature_class":"P",
    "gn:feature_code":"PPL",
    "gn:name":"Armara",
    "gn:population":0,
    "gn:timezone":"Africa/Asmara",
    "iso:country":"ER",
    "wof:name":"Armara",
    "wof:placetype":"locality"
},
  "geometry": {"coordinates":[37.3564,15.25675],"type":"Point"}
}