{
  "type": "Feature",
  "properties": {
    "gn:admin1_code":"00",
    "gn:asciiname":"Addi Nefas",
    "gn:country_code":"ER",
    "gn:dem":1706,
    "gn:feature_class":"P",
    "gn:feature_code":"PPL",
    "gn:name":"Addi Nefas",
    "gn:population":0,
    "gn:timezone":"Africa/Asmara",
    "iso:country":"ER",
    "wof:name":"Addi Nefas",
    "wof:placetype":"locality"
},
  "geometry": {"coordinates":[38.445,14.87278],"type":"Point"}
}