{
  "type": "Feature",
  "properties": {
    "gn:admin1_code":"00",
    "gn:asciiname":"Mai Tzagla",
    "gn:country_code":"ER",
    "gn:dem":2299,
    "gn:feature_class":"P",
    "gn:feature_code":"PPL",
    "gn:name":"Mai Tzagla",
    "gn:population":0,
    "gn:timezone":"Africa/Asmara",
    "iso:country":"ER",
    "name:und_x_variant":[
        "May Tsagla",
        "Mai Tzagla"
    ],
    "wof:name":"Mai Tzagla",
    "wof:placetype":"locality"
},
  "geometry": {"coordinates":[39.3825,14.59472],"type":"Point"}
}