{
  "type": "Feature",
  "properties": {
    "gn:admin1_code":"05",
    "gn:asciiname":"Mek'erka",
    "gn:country_code":"ER",
    "gn:dem":2344,
    "gn:feature_class":"P",
    "gn:feature_code":"PPL",
    "gn:name":"Mek\u2019erka",
    "gn:population":0,
    "gn:timezone":"Africa/Asmara",
    "iso:country":"ER",
    "name:und_x_variant":[
        "Mek\u2019erka (2)",
        "Mek\u2019erka"
    ],
    "wof:name":"Mek'erka",
    "wof:placetype":"locality"
},
  "geometry": {"coordinates":[38.85005,15.46518],"type":"Point"}
}