{
  "type": "Feature",
  "properties": {
    "gn:admin1_code":"00",
    "gn:asciiname":"Hacal Todaro",
    "gn:country_code":"ER",
    "gn:dem":359,
    "gn:feature_class":"P",
    "gn:feature_code":"PPL",
    "gn:name":"Hacal Todaro",
    "gn:population":0,
    "gn:timezone":"Africa/Asmara",
    "iso:country":"ER",
    "wof:name":"Hacal Todaro",
    "wof:placetype":"locality"
},
  "geometry": {"coordinates":[37.55,17.16667],"type":"Point"}
}