{
  "type": "Feature",
  "properties": {
    "gn:admin1_code":"06",
    "gn:asciiname":"Gandeli",
    "gn:country_code":"ER",
    "gn:dem":32,
    "gn:feature_class":"P",
    "gn:feature_code":"PPL",
    "gn:name":"Gandeli",
    "gn:population":0,
    "gn:timezone":"Africa/Asmara",
    "iso:country":"ER",
    "wof:name":"Gandeli",
    "wof:placetype":"locality"
},
  "geometry": {"coordinates":[39.88333,15.41667],"type":"Point"}
}