{
  "type": "Feature",
  "properties": {
    "gn:admin1_code":"02",
    "gn:asciiname":"Euanet",
    "gn:country_code":"ER",
    "gn:dem":2103,
    "gn:feature_class":"P",
    "gn:feature_code":"PPL",
    "gn:name":"Euanet",
    "gn:population":0,
    "gn:timezone":"Africa/Asmara",
    "iso:country":"ER",
    "wof:name":"Euanet",
    "wof:placetype":"locality"
},
  "geometry": {"coordinates":[39.18723,14.99877],"type":"Point"}
}