{
  "type": "Feature",
  "properties": {
    "gn:admin1_code":"02",
    "gn:asciiname":"Ziban Una",
    "gn:country_code":"ER",
    "gn:dem":1957,
    "gn:feature_class":"P",
    "gn:feature_code":"PPL",
    "gn:name":"Ziban Una",
    "gn:population":0,
    "gn:timezone":"Africa/Asmara",
    "iso:country":"ER",
    "name:und_x_variant":[
        "Zeban Ona",
        "Ziban Una"
    ],
    "wof:name":"Ziban Una",
    "wof:placetype":"locality"
},
  "geometry": {"coordinates":[38.81583,14.85917],"type":"Point"}
}