{
  "type": "Feature",
  "properties": {
    "gn:admin1_code":"02",
    "gn:asciiname":"Hishkib",
    "gn:country_code":"ER",
    "gn:dem":1068,
    "gn:feature_class":"P",
    "gn:feature_code":"PPL",
    "gn:name":"Hishkib",
    "gn:population":0,
    "gn:timezone":"Africa/Asmara",
    "iso:country":"ER",
    "wof:name":"Hishkib",
    "wof:placetype":"locality"
},
  "geometry": {"coordinates":[38.32301,17.15401],"type":"Point"}
}