{
  "type": "Feature",
  "properties": {
    "gn:admin1_code":"02",
    "gn:asciiname":"Adi Felleho",
    "gn:country_code":"ER",
    "gn:dem":1790,
    "gn:feature_class":"P",
    "gn:feature_code":"PPL",
    "gn:name":"Adi Felleho",
    "gn:population":0,
    "gn:timezone":"Africa/Asmara",
    "iso:country":"ER",
    "name:und_x_variant":[
        "Adi Fellekho",
        "Adi Felleho"
    ],
    "wof:name":"Adi Felleho",
    "wof:placetype":"locality"
},
  "geometry": {"coordinates":[38.55111,14.84083],"type":"Point"}
}