{
  "type": "Feature",
  "properties": {
    "gn:admin1_code":"06",
    "gn:asciiname":"Agametta",
    "gn:country_code":"ER",
    "gn:dem":893,
    "gn:feature_class":"P",
    "gn:feature_code":"PPL",
    "gn:name":"Agametta",
    "gn:population":0,
    "gn:timezone":"Africa/Asmara",
    "iso:country":"ER",
    "wof:name":"Agametta",
    "wof:placetype":"locality"
},
  "geometry": {"coordinates":[39.30046,15.37157],"type":"Point"}
}