{
  "type": "Feature",
  "properties": {
    "gn:admin1_code":"05",
    "gn:asciiname":"Af Delu",
    "gn:country_code":"ER",
    "gn:dem":2474,
    "gn:feature_class":"P",
    "gn:feature_code":"PPL",
    "gn:name":"Af Delu",
    "gn:population":0,
    "gn:timezone":"Africa/Asmara",
    "iso:country":"ER",
    "wof:name":"Af Delu",
    "wof:placetype":"locality"
},
  "geometry": {"coordinates":[38.85913,15.50121],"type":"Point"}
}