{
  "type": "Feature",
  "properties": {
    "gn:admin1_code":"03",
    "gn:asciiname":"Hallol",
    "gn:country_code":"ER",
    "gn:dem":211,
    "gn:feature_class":"P",
    "gn:feature_code":"PPL",
    "gn:name":"Hallol",
    "gn:population":0,
    "gn:timezone":"Africa/Asmara",
    "iso:country":"ER",
    "name:und_x_variant":[
        "Haloll",
        "H\u00e0lol"
    ],
    "wof:name":"Hallol",
    "wof:placetype":"locality"
},
  "geometry": {"coordinates":[41.07191,14.41581],"type":"Point"}
}