{
  "type": "Feature",
  "properties": {
    "gn:admin1_code":"05",
    "gn:asciiname":"Redoy",
    "gn:country_code":"ER",
    "gn:dem":2207,
    "gn:feature_class":"P",
    "gn:feature_code":"PPL",
    "gn:name":"Redoy",
    "gn:population":0,
    "gn:timezone":"Africa/Asmara",
    "iso:country":"ER",
    "wof:name":"Redoy",
    "wof:placetype":"locality"
},
  "geometry": {"coordinates":[38.79325,15.24989],"type":"Point"}
}