{
  "type": "Feature",
  "properties": {
    "gn:admin1_code":"02",
    "gn:asciiname":"Adi Neduk",
    "gn:country_code":"ER",
    "gn:dem":2081,
    "gn:feature_class":"P",
    "gn:feature_code":"PPL",
    "gn:name":"Adi Neduk",
    "gn:population":0,
    "gn:timezone":"Africa/Asmara",
    "iso:country":"ER",
    "wof:name":"Adi Neduk",
    "wof:placetype":"locality"
},
  "geometry": {"coordinates":[38.65361,14.88056],"type":"Point"}
}