{
  "type": "Feature",
  "properties": {
    "gn:admin1_code":"06",
    "gn:asciiname":"Marakabet",
    "gn:country_code":"ER",
    "gn:dem":1882,
    "gn:feature_class":"P",
    "gn:feature_code":"PPL",
    "gn:name":"Marakabet",
    "gn:population":0,
    "gn:timezone":"Africa/Asmara",
    "iso:country":"ER",
    "wof:name":"Marakabet",
    "wof:placetype":"locality"
},
  "geometry": {"coordinates":[38.76613,15.85971],"type":"Point"}
}