{
  "type": "Feature",
  "properties": {
    "gn:admin1_code":"02",
    "gn:asciiname":"Merra Nahayne",
    "gn:country_code":"ER",
    "gn:dem":1888,
    "gn:feature_class":"P",
    "gn:feature_code":"PPL",
    "gn:name":"Merra Nahayne",
    "gn:population":0,
    "gn:timezone":"Africa/Asmara",
    "iso:country":"ER",
    "name:und_x_variant":[
        "Merra Nakhayne",
        "Merra Nahayne"
    ],
    "wof:name":"Merra Nahayne",
    "wof:placetype":"locality"
},
  "geometry": {"coordinates":[39.22361,14.8075],"type":"Point"}
}