{
  "type": "Feature",
  "properties": {
    "gn:admin1_code":"02",
    "gn:asciiname":"Khokho",
    "gn:country_code":"ER",
    "gn:dem":1853,
    "gn:feature_class":"P",
    "gn:feature_code":"PPL",
    "gn:name":"Khokho",
    "gn:population":0,
    "gn:timezone":"Africa/Asmara",
    "iso:country":"ER",
    "wof:name":"Khokho",
    "wof:placetype":"locality"
},
  "geometry": {"coordinates":[38.41466,16.42749],"type":"Point"}
}