{
  "type": "Feature",
  "properties": {
    "gn:admin1_code":"02",
    "gn:asciiname":"Obellet",
    "gn:country_code":"ER",
    "gn:dem":14,
    "gn:feature_class":"P",
    "gn:feature_code":"PPL",
    "gn:name":"Obellet",
    "gn:population":0,
    "gn:timezone":"Africa/Asmara",
    "iso:country":"ER",
    "name:und_x_variant":[
        "Qbellet",
        "Obellet"
    ],
    "wof:name":"Obellet",
    "wof:placetype":"locality"
},
  "geometry": {"coordinates":[39.19044,16.2556],"type":"Point"}
}