{
  "type": "Feature",
  "properties": {
    "gn:admin1_code":"02",
    "gn:asciiname":"Ala",
    "gn:country_code":"ER",
    "gn:dem":1720,
    "gn:feature_class":"P",
    "gn:feature_code":"PPL",
    "gn:name":"\u0100la",
    "gn:population":0,
    "gn:timezone":"Africa/Asmara",
    "iso:country":"ER",
    "name:und_x_variant":[
        "\u0100la (1)",
        "\u0100la"
    ],
    "wof:name":"Ala",
    "wof:placetype":"locality"
},
  "geometry": {"coordinates":[39.03673,15.18507],"type":"Point"}
}