{
  "type": "Feature",
  "properties": {
    "gn:admin1_code":"04",
    "gn:asciiname":"May-Mefals",
    "gn:country_code":"ER",
    "gn:dem":1587,
    "gn:feature_class":"P",
    "gn:feature_code":"PPL",
    "gn:name":"May-Mefals",
    "gn:population":0,
    "gn:timezone":"Africa/Asmara",
    "iso:country":"ER",
    "name:und_x_variant":[
        "Mai Mefales",
        "May Mekhales",
        "May-Mefals"
    ],
    "wof:name":"May-Mefals",
    "wof:placetype":"locality"
},
  "geometry": {"coordinates":[38.2675,14.98667],"type":"Point"}
}