{
  "type": "Feature",
  "properties": {
    "gn:admin1_code":"02",
    "gn:asciiname":"Addekemene",
    "gn:country_code":"ER",
    "gn:dem":2044,
    "gn:feature_class":"P",
    "gn:feature_code":"PPL",
    "gn:name":"Addekemene",
    "gn:population":0,
    "gn:timezone":"Africa/Asmara",
    "iso:country":"ER",
    "wof:name":"Addekemene",
    "wof:placetype":"locality"
},
  "geometry": {"coordinates":[38.7775,14.92639],"type":"Point"}
}