{
  "type": "Feature",
  "properties": {
    "gn:admin1_code":"04",
    "gn:asciiname":"Lama",
    "gn:country_code":"ER",
    "gn:dem":737,
    "gn:feature_class":"P",
    "gn:feature_code":"PPL",
    "gn:name":"Lama",
    "gn:population":0,
    "gn:timezone":"Africa/Asmara",
    "iso:country":"ER",
    "wof:name":"Lama",
    "wof:placetype":"locality"
},
  "geometry": {"coordinates":[37.24279,15.04633],"type":"Point"}
}