{
  "type": "Feature",
  "properties": {
    "gn:admin1_code":"03",
    "gn:asciiname":"Memla",
    "gn:country_code":"ER",
    "gn:dem":5,
    "gn:feature_class":"P",
    "gn:feature_code":"PPL",
    "gn:name":"Memla",
    "gn:population":0,
    "gn:timezone":"Africa/Asmara",
    "iso:country":"ER",
    "wof:name":"Memla",
    "wof:placetype":"locality"
},
  "geometry": {"coordinates":[40.4026,15.62827],"type":"Point"}
}