{
  "type": "Feature",
  "properties": {
    "gn:admin1_code":"04",
    "gn:asciiname":"Shiderda",
    "gn:country_code":"ER",
    "gn:dem":970,
    "gn:feature_class":"P",
    "gn:feature_code":"PPL",
    "gn:name":"Shiderda",
    "gn:population":0,
    "gn:timezone":"Africa/Asmara",
    "iso:country":"ER",
    "wof:name":"Shiderda",
    "wof:placetype":"locality"
},
  "geometry": {"coordinates":[37.58859,15.1901],"type":"Point"}
}