{
  "type": "Feature",
  "properties": {
    "gn:admin1_code":"00",
    "gn:asciiname":"Denagul",
    "gn:country_code":"ER",
    "gn:dem":2164,
    "gn:feature_class":"P",
    "gn:feature_code":"PPL",
    "gn:name":"Denagul",
    "gn:population":0,
    "gn:timezone":"Africa/Asmara",
    "iso:country":"ER",
    "name:und_x_variant":[
        "Denagur",
        "Denagul"
    ],
    "wof:name":"Denagul",
    "wof:placetype":"locality"
},
  "geometry": {"coordinates":[39.34278,14.69194],"type":"Point"}
}