{
  "type": "Feature",
  "properties": {
    "gn:admin1_code":"06",
    "gn:asciiname":"Kulul",
    "gn:country_code":"ER",
    "gn:dem":-112,
    "gn:feature_class":"P",
    "gn:feature_code":"PPL",
    "gn:name":"Kulul",
    "gn:population":0,
    "gn:timezone":"Africa/Asmara",
    "iso:country":"ER",
    "name:ita_x_preferred":[
        "Cululli"
    ],
    "name:rus_x_preferred":[
        "\u041a\u043e\u043b\u0443\u043b\u043b\u0438"
    ],
    "name:und_x_variant":[
        "Culculli",
        "Kululli",
        "Colulli",
        "Kolulli",
        "Kulul",
        "Kuleli",
        "Colluli"
    ],
    "wof:name":"Kulul",
    "wof:placetype":"locality"
},
  "geometry": {"coordinates":[40.35149000000001,14.37474],"type":"Point"}
}