{
  "type": "Feature",
  "properties": {
    "gn:admin1_code":"02",
    "gn:asciiname":"Addi-Nedi",
    "gn:country_code":"ER",
    "gn:dem":1963,
    "gn:feature_class":"P",
    "gn:feature_code":"PPL",
    "gn:name":"Addi-Nedi",
    "gn:population":0,
    "gn:timezone":"Africa/Asmara",
    "iso:country":"ER",
    "wof:name":"Addi-Nedi",
    "wof:placetype":"locality"
},
  "geometry": {"coordinates":[38.56907,15.0471],"type":"Point"}
}