{
  "type": "Feature",
  "properties": {
    "gn:admin1_code":"03",
    "gn:asciiname":"Irble",
    "gn:country_code":"ER",
    "gn:dem":467,
    "gn:feature_class":"P",
    "gn:feature_code":"PPL",
    "gn:name":"Irble",
    "gn:population":0,
    "gn:timezone":"Africa/Asmara",
    "iso:country":"ER",
    "wof:name":"Irble",
    "wof:placetype":"locality"
},
  "geometry": {"coordinates":[41.54852,13.74785],"type":"Point"}
}