{
  "type": "Feature",
  "properties": {
    "gn:admin1_code":"02",
    "gn:asciiname":"Ambacocat",
    "gn:country_code":"ER",
    "gn:dem":1896,
    "gn:feature_class":"P",
    "gn:feature_code":"PPL",
    "gn:name":"Ambacocat",
    "gn:population":0,
    "gn:timezone":"Africa/Asmara",
    "iso:country":"ER",
    "name:und_x_variant":[
        "Ambakokat",
        "Ambacocat"
    ],
    "wof:name":"Ambacocat",
    "wof:placetype":"locality"
},
  "geometry": {"coordinates":[39.25833,14.85056],"type":"Point"}
}