{
  "type": "Feature",
  "properties": {
    "gn:admin1_code":"06",
    "gn:asciiname":"Agbalo",
    "gn:country_code":"ER",
    "gn:dem":141,
    "gn:feature_class":"P",
    "gn:feature_code":"PPL",
    "gn:name":"Agbalo",
    "gn:population":0,
    "gn:timezone":"Africa/Asmara",
    "iso:country":"ER",
    "wof:name":"Agbalo",
    "wof:placetype":"locality"
},
  "geometry": {"coordinates":[39.30709,15.56997],"type":"Point"}
}