{
  "type": "Feature",
  "properties": {
    "gn:admin1_code":"06",
    "gn:asciiname":"Tantarua",
    "gn:country_code":"ER",
    "gn:dem":1364,
    "gn:feature_class":"P",
    "gn:feature_code":"PPL",
    "gn:name":"Tantarua",
    "gn:population":0,
    "gn:timezone":"Africa/Asmara",
    "iso:country":"ER",
    "name:und_x_variant":[
        "Tantarna",
        "Tantarua"
    ],
    "wof:name":"Tantarua",
    "wof:placetype":"locality"
},
  "geometry": {"coordinates":[38.46142,15.79546],"type":"Point"}
}