{
  "type": "Feature",
  "properties": {
    "gn:admin1_code":"02",
    "gn:asciiname":"Habenat",
    "gn:country_code":"ER",
    "gn:dem":1580,
    "gn:feature_class":"P",
    "gn:feature_code":"PPL",
    "gn:name":"Habenat",
    "gn:population":0,
    "gn:timezone":"Africa/Asmara",
    "iso:country":"ER",
    "name:und_x_variant":[
        "Habcnat",
        "Habenat"
    ],
    "wof:name":"Habenat",
    "wof:placetype":"locality"
},
  "geometry": {"coordinates":[39.07917,14.79639],"type":"Point"}
}