{
  "type": "Feature",
  "properties": {
    "gn:admin1_code":"00",
    "gn:asciiname":"Awgaro",
    "gn:country_code":"ER",
    "gn:dem":817,
    "gn:feature_class":"P",
    "gn:feature_code":"PPL",
    "gn:name":"Awgaro",
    "gn:population":0,
    "gn:timezone":"Africa/Asmara",
    "iso:country":"ER",
    "name:und_x_variant":[
        "Ugaro",
        "Ugolo",
        "Awgaro"
    ],
    "wof:name":"Awgaro",
    "wof:placetype":"locality"
},
  "geometry": {"coordinates":[37.44111,14.82444],"type":"Point"}
}