{
  "type": "Feature",
  "properties": {
    "gn:admin1_code":"02",
    "gn:asciiname":"Ashira",
    "gn:country_code":"ER",
    "gn:dem":1793,
    "gn:feature_class":"P",
    "gn:feature_code":"PPL",
    "gn:name":"Ashira",
    "gn:population":0,
    "gn:timezone":"Africa/Asmara",
    "iso:country":"ER",
    "wof:name":"Ashira",
    "wof:placetype":"locality"
},
  "geometry": {"coordinates":[39.25667,14.78139],"type":"Point"}
}