{
  "type": "Feature",
  "properties": {
    "gn:admin1_code":"02",
    "gn:asciiname":"Mihiyaw",
    "gn:country_code":"ER",
    "gn:dem":1889,
    "gn:feature_class":"P",
    "gn:feature_code":"PPL",
    "gn:name":"Mihiyaw",
    "gn:population":0,
    "gn:timezone":"Africa/Asmara",
    "iso:country":"ER",
    "name:und_x_variant":[
        "Mekhian",
        "Mihiyaw"
    ],
    "wof:name":"Mihiyaw",
    "wof:placetype":"locality"
},
  "geometry": {"coordinates":[38.83139,14.73833],"type":"Point"}
}