{
  "type": "Feature",
  "properties": {
    "gn:admin1_code":"00",
    "gn:asciiname":"Addi Toqualu",
    "gn:country_code":"ER",
    "gn:dem":1551,
    "gn:feature_class":"P",
    "gn:feature_code":"PPL",
    "gn:name":"Addi Toqualu",
    "gn:population":0,
    "gn:timezone":"Africa/Asmara",
    "iso:country":"ER",
    "name:und_x_variant":[
        "Addi Uollo",
        "Addi Tokualu",
        "Addi Toqualu"
    ],
    "wof:name":"Addi Toqualu",
    "wof:placetype":"locality"
},
  "geometry": {"coordinates":[38.42472,14.91],"type":"Point"}
}