{
  "type": "Feature",
  "properties": {
    "gn:admin1_code":"02",
    "gn:asciiname":"Adibara",
    "gn:country_code":"ER",
    "gn:dem":2020,
    "gn:feature_class":"P",
    "gn:feature_code":"PPL",
    "gn:name":"\u0100d\u012bbara",
    "gn:population":0,
    "gn:timezone":"Africa/Asmara",
    "iso:country":"ER",
    "name:und_x_variant":[
        "Adi Baro",
        "\u0100d\u012bbara"
    ],
    "wof:name":"Adibara",
    "wof:placetype":"locality"
},
  "geometry": {"coordinates":[38.78385,15.13994],"type":"Point"}
}