{
  "type": "Feature",
  "properties": {
    "gn:admin1_code":"06",
    "gn:asciiname":"Betalifuru",
    "gn:country_code":"ER",
    "gn:dem":181,
    "gn:feature_class":"P",
    "gn:feature_code":"PPL",
    "gn:name":"Betalifuru",
    "gn:population":0,
    "gn:timezone":"Africa/Asmara",
    "iso:country":"ER",
    "wof:name":"Betalifuru",
    "wof:placetype":"locality"
},
  "geometry": {"coordinates":[39.52327,15.35818],"type":"Point"}
}