{
  "type": "Feature",
  "properties": {
    "gn:admin1_code":"00",
    "gn:asciiname":"Zigfet",
    "gn:country_code":"ER",
    "gn:dem":2243,
    "gn:feature_class":"P",
    "gn:feature_code":"PPL",
    "gn:name":"Zigfet",
    "gn:population":0,
    "gn:timezone":"Africa/Asmara",
    "iso:country":"ER",
    "wof:name":"Zigfet",
    "wof:placetype":"locality"
},
  "geometry": {"coordinates":[39.41139,14.59694],"type":"Point"}
}