{
  "type": "Feature",
  "properties": {
    "gn:admin1_code":"05",
    "gn:asciiname":"Shigirni",
    "gn:country_code":"ER",
    "gn:dem":1868,
    "gn:feature_class":"P",
    "gn:feature_code":"PPL",
    "gn:name":"Shigirn\u012b",
    "gn:population":0,
    "gn:timezone":"Africa/Asmara",
    "iso:country":"ER",
    "wof:name":"Shigirni",
    "wof:placetype":"locality"
},
  "geometry": {"coordinates":[38.99194,15.36667],"type":"Point"}
}