{
  "type": "Feature",
  "properties": {
    "gn:admin1_code":"06",
    "gn:asciiname":"Lammagadi",
    "gn:country_code":"ER",
    "gn:dem":17,
    "gn:feature_class":"P",
    "gn:feature_code":"PPL",
    "gn:name":"Lammagadi",
    "gn:population":0,
    "gn:timezone":"Africa/Asmara",
    "iso:country":"ER",
    "wof:name":"Lammagadi",
    "wof:placetype":"locality"
},
  "geometry": {"coordinates":[39.81042,15.36715],"type":"Point"}
}