{
  "type": "Feature",
  "properties": {
    "gn:admin1_code":"06",
    "gn:asciiname":"Menuetet",
    "gn:country_code":"ER",
    "gn:dem":438,
    "gn:feature_class":"P",
    "gn:feature_code":"PPL",
    "gn:name":"Menuetet",
    "gn:population":0,
    "gn:timezone":"Africa/Asmara",
    "iso:country":"ER",
    "name:und_x_variant":[
        "Menuztet"
    ],
    "wof:name":"Menuetet",
    "wof:placetype":"locality"
},
  "geometry": {"coordinates":[38.967,15.68738],"type":"Point"}
}