{
  "type": "Feature",
  "properties": {
    "gn:admin1_code":"02",
    "gn:asciiname":"Ad Deka Takla",
    "gn:country_code":"ER",
    "gn:dem":2241,
    "gn:feature_class":"P",
    "gn:feature_code":"PPL",
    "gn:name":"Ad Deka Takla",
    "gn:population":0,
    "gn:timezone":"Africa/Asmara",
    "iso:country":"ER",
    "wof:name":"Ad Deka Takla",
    "wof:placetype":"locality"
},
  "geometry": {"coordinates":[38.71352,15.02263],"type":"Point"}
}