{
  "type": "Feature",
  "properties": {
    "gn:admin1_code":"02",
    "gn:asciiname":"Dekabadru",
    "gn:country_code":"ER",
    "gn:dem":2180,
    "gn:feature_class":"P",
    "gn:feature_code":"PPL",
    "gn:name":"Dekabadru",
    "gn:population":0,
    "gn:timezone":"Africa/Asmara",
    "iso:country":"ER",
    "wof:name":"Dekabadru",
    "wof:placetype":"locality"
},
  "geometry": {"coordinates":[39.09071,15.07241],"type":"Point"}
}