{
  "type": "Feature",
  "properties": {
    "gn:admin1_code":"02",
    "gn:asciiname":"Tukul' Salet",
    "gn:country_code":"ER",
    "gn:dem":1582,
    "gn:feature_class":"P",
    "gn:feature_code":"PPL",
    "gn:name":"Tukul\u2019 Salet",
    "gn:population":0,
    "gn:timezone":"Africa/Asmara",
    "iso:country":"ER",
    "name:rus_x_preferred":[
        "Tukul\u2019 Salet"
    ],
    "wof:name":"Tukul' Salet",
    "wof:placetype":"locality"
},
  "geometry": {"coordinates":[39.1915,15.10301],"type":"Point"}
}