{
  "type": "Feature",
  "properties": {
    "gn:admin1_code":"02",
    "gn:asciiname":"Obellet",
    "gn:country_code":"ER",
    "gn:dem":219,
    "gn:feature_class":"P",
    "gn:feature_code":"PPL",
    "gn:name":"Obellet",
    "gn:population":0,
    "gn:timezone":"Africa/Asmara",
    "iso:country":"ER",
    "wof:name":"Obellet",
    "wof:placetype":"locality"
},
  "geometry": {"coordinates":[38.94244000000001,16.14017999999999],"type":"Point"}
}