{
  "type": "Feature",
  "properties": {
    "gn:admin1_code":"01",
    "gn:asciiname":"Azafa",
    "gn:country_code":"ER",
    "gn:dem":1555,
    "gn:feature_class":"P",
    "gn:feature_code":"PPL",
    "gn:name":"Azafa",
    "gn:population":0,
    "gn:timezone":"Africa/Asmara",
    "iso:country":"ER",
    "wof:name":"Azafa",
    "wof:placetype":"locality"
},
  "geometry": {"coordinates":[38.59318,15.77207],"type":"Point"}
}