{
  "type": "Feature",
  "properties": {
    "gn:admin1_code":"02",
    "gn:asciiname":"Adi Kuoshet",
    "gn:country_code":"ER",
    "gn:dem":1749,
    "gn:feature_class":"P",
    "gn:feature_code":"PPL",
    "gn:name":"Adi Kuoshet",
    "gn:population":0,
    "gn:timezone":"Africa/Asmara",
    "iso:country":"ER",
    "wof:name":"Adi Kuoshet",
    "wof:placetype":"locality"
},
  "geometry": {"coordinates":[38.61278,14.84222],"type":"Point"}
}