{
  "type": "Feature",
  "properties": {
    "gn:admin1_code":"02",
    "gn:asciiname":"Ila Babu",
    "gn:country_code":"ER",
    "gn:dem":1141,
    "gn:feature_class":"P",
    "gn:feature_code":"PPL",
    "gn:name":"Ila Babu",
    "gn:population":0,
    "gn:timezone":"Africa/Asmara",
    "iso:country":"ER",
    "wof:name":"Ila Babu",
    "wof:placetype":"locality"
},
  "geometry": {"coordinates":[38.10575,17.25396],"type":"Point"}
}