{
  "type": "Feature",
  "properties": {
    "gn:admin1_code":"06",
    "gn:asciiname":"Rarodetta",
    "gn:country_code":"ER",
    "gn:dem":720,
    "gn:feature_class":"P",
    "gn:feature_code":"PPL",
    "gn:name":"Rarodetta",
    "gn:population":0,
    "gn:timezone":"Africa/Asmara",
    "iso:country":"ER",
    "wof:name":"Rarodetta",
    "wof:placetype":"locality"
},
  "geometry": {"coordinates":[39.35295,15.3886],"type":"Point"}
}