{
  "type": "Feature",
  "properties": {
    "gn:admin1_code":"02",
    "gn:asciiname":"Tafo",
    "gn:country_code":"ER",
    "gn:dem":1274,
    "gn:feature_class":"P",
    "gn:feature_code":"PPL",
    "gn:name":"Tafo",
    "gn:population":0,
    "gn:timezone":"Africa/Asmara",
    "iso:country":"ER",
    "name:aka_x_preferred":[
        "Tafo"
    ],
    "name:ceb_x_preferred":[
        "Tafo"
    ],
    "name:deu_x_preferred":[
        "Tafo"
    ],
    "name:spa_x_preferred":[
        "New Tafo"
    ],
    "name:swe_x_preferred":[
        "Tafo"
    ],
    "name:urd_x_preferred":[
        "\u062a\u0627\u0641\u0648"
    ],
    "wof:name":"Tafo",
    "wof:placetype":"locality"
},
  "geometry": {"coordinates":[39.39325,15.05069],"type":"Point"}
}