{
  "type": "Feature",
  "properties": {
    "gn:admin1_code":"02",
    "gn:asciiname":"Adi Bahro",
    "gn:country_code":"ER",
    "gn:dem":2020,
    "gn:feature_class":"P",
    "gn:feature_code":"PPL",
    "gn:name":"\u0100d\u012b Bahro",
    "gn:population":0,
    "gn:timezone":"Africa/Asmara",
    "iso:country":"ER",
    "name:und_x_variant":[
        "Addi Bakhro",
        "\u0100d\u012b Bahro"
    ],
    "wof:name":"Adi Bahro",
    "wof:placetype":"locality"
},
  "geometry": {"coordinates":[38.87194,14.66139],"type":"Point"}
}