{
  "type": "Feature",
  "properties": {
    "gn:admin1_code":"02",
    "gn:asciiname":"Mikrem",
    "gn:country_code":"ER",
    "gn:dem":1894,
    "gn:feature_class":"P",
    "gn:feature_code":"PPL",
    "gn:name":"Mikrem",
    "gn:population":0,
    "gn:timezone":"Africa/Asmara",
    "iso:country":"ER",
    "name:und_x_variant":[
        "Mekrem",
        "Mikrem"
    ],
    "wof:name":"Mikrem",
    "wof:placetype":"locality"
},
  "geometry": {"coordinates":[38.8325,14.77667],"type":"Point"}
}