{
  "type": "Feature",
  "properties": {
    "gn:admin1_code":"02",
    "gn:asciiname":"Skrofoto",
    "gn:country_code":"ER",
    "gn:dem":2123,
    "gn:feature_class":"P",
    "gn:feature_code":"PPL",
    "gn:name":"Skrofoto",
    "gn:population":0,
    "gn:timezone":"Africa/Asmara",
    "iso:country":"ER",
    "wof:name":"Skrofoto",
    "wof:placetype":"locality"
},
  "geometry": {"coordinates":[38.83055,15.17464],"type":"Point"}
}