{
  "type": "Feature",
  "properties": {
    "gn:admin1_code":"04",
    "gn:asciiname":"Deca Dascim",
    "gn:country_code":"ER",
    "gn:dem":2142,
    "gn:feature_class":"P",
    "gn:feature_code":"PPL",
    "gn:name":"Deca Dascim",
    "gn:population":0,
    "gn:timezone":"Africa/Asmara",
    "iso:country":"ER",
    "wof:name":"Deca Dascim",
    "wof:placetype":"locality"
},
  "geometry": {"coordinates":[38.69883,15.38633],"type":"Point"}
}