{
  "type": "Feature",
  "properties": {
    "iso:country":"ER",
    "name:ara_x_preferred":[
        "\u0628\u0627\u0631\u0646\u062a\u0648"
    ],
    "name:azb_x_preferred":[
        "\u0628\u0627\u0631\u0646\u062a\u0648"
    ],
    "name:bul_x_preferred":[
        "\u0411\u0430\u0440\u0435\u043d\u0442\u0443"
    ],
    "name:ceb_x_preferred":[
        "Barentu"
    ],
    "name:deu_x_preferred":[
        "Barentu"
    ],
    "name:eng_x_preferred":[
        "Barentu"
    ],
    "name:fas_x_preferred":[
        "\u0628\u0627\u0631\u0646\u062a\u0648"
    ],
    "name:fin_x_preferred":[
        "Barentu"
    ],
    "name:fra_x_preferred":[
        "Barentu"
    ],
    "name:ita_x_preferred":[
        "Barent\u00f9"
    ],
    "name:jpn_x_preferred":[
        "\u30d0\u30ec\u30f3\u30c4"
    ],
    "name:kat_x_preferred":[
        "\u10d1\u10d0\u10e0\u10d4\u10dc\u10e2\u10e3"
    ],
    "name:kor_x_preferred":[
        "\ubc14\ub80c\ud22c"
    ],
    "name:lit_x_preferred":[
        "Barentu"
    ],
    "name:ltz_x_preferred":[
        "Barentu"
    ],
    "name:nld_x_preferred":[
        "Barentu"
    ],
    "name:nob_x_preferred":[
        "Barentu"
    ],
    "name:nor_x_preferred":[
        "Barentu"
    ],
    "name:pol_x_preferred":[
        "Barentu"
    ],
    "name:por_x_preferred":[
        "Barentu"
    ],
    "name:ron_x_preferred":[
        "Barentu"
    ],
    "name:rus_x_preferred":[
        "\u0411\u0430\u0440\u044d\u043d\u0442\u0443"
    ],
    "name:swe_x_preferred":[
        "Barentu"
    ],
    "name:tir_x_preferred":[
        "\u1263\u1228\u1295\u1271"
    ],
    "name:tir_x_variant":[
        "Barentu"
    ],
    "name:ukr_x_preferred":[
        "\u0411\u0430\u0440\u0435\u043d\u0442\u0443"
    ],
    "name:und_x_variant":[
        "Mai Tsada"
    ],
    "name:urd_x_preferred":[
        "\u0628\u0627\u0631\u06cc\u0646\u062a\u0648\u060c \u0627\u0631\u062a\u0631\u06cc\u0627"
    ],
    "name:urd_x_variant":[
        "\u0628\u0627\u0631\u06cc\u0646\u062a\u0648"
    ],
    "name:yue_x_preferred":[
        "\u5df4\u502b\u5716"
    ],
    "name:zho_x_preferred":[
        "\u5df4\u502b\u5716"
    ],
    "qs:gn_country":"ER",
    "qs:gn_fcode":"PPLA",
    "qs:gn_pop":15891,
    "qs:name":"Barentu",
    "qs:name_adm0":"Eritrea",
    "qs:name_adm1":"Gash-Barka",
    "qs:photos":0,
    "qs:photos_1k":0,
    "qs:photos_9k":1,
    "qs:photos_9r":1,
    "qs:photos_all":25,
    "qs:photos_sr":0,
    "qs:placetype":"Town",
    "qs:pop_sr":"6",
    "qs:woe_adm0":23424806,
    "wd:wordcount":425,
    "wof:name":"Barentu",
    "wof:placetype":"locality",
    "wof:population":15891
},
  "geometry": {"coordinates":[37.59067,15.10582],"type":"Point"}
}