{
  "type": "Feature",
  "properties": {
    "gn:admin1_code":"05",
    "gn:asciiname":"Goorbaati",
    "gn:country_code":"ER",
    "gn:dem":2103,
    "gn:feature_class":"P",
    "gn:feature_code":"PPL",
    "gn:name":"Goorbaati",
    "gn:population":0,
    "gn:timezone":"Africa/Asmara",
    "iso:country":"ER",
    "wof:name":"Goorbaati",
    "wof:placetype":"locality"
},
  "geometry": {"coordinates":[38.89459,15.16344],"type":"Point"}
}