{
  "type": "Feature",
  "properties": {
    "gn:admin1_code":"02",
    "gn:asciiname":"Kutur",
    "gn:country_code":"ER",
    "gn:dem":1966,
    "gn:feature_class":"P",
    "gn:feature_code":"PPL",
    "gn:name":"Kutur",
    "gn:population":0,
    "gn:timezone":"Africa/Asmara",
    "iso:country":"ER",
    "wof:name":"Kutur",
    "wof:placetype":"locality"
},
  "geometry": {"coordinates":[38.8325,14.66194],"type":"Point"}
}