{
  "type": "Feature",
  "properties": {
    "gn:admin1_code":"06",
    "gn:asciiname":"Bordele",
    "gn:country_code":"ER",
    "gn:dem":30,
    "gn:feature_class":"P",
    "gn:feature_code":"PPL",
    "gn:name":"Bordele",
    "gn:population":0,
    "gn:timezone":"Africa/Asmara",
    "iso:country":"ER",
    "name:und_x_variant":[
        "Bardoli",
        "Bordele"
    ],
    "wof:name":"Bordele",
    "wof:placetype":"locality"
},
  "geometry": {"coordinates":[39.91111,15.15444],"type":"Point"}
}