{
  "type": "Feature",
  "properties": {
    "gn:admin1_code":"02",
    "gn:asciiname":"Enda Ekkise",
    "gn:country_code":"ER",
    "gn:dem":2065,
    "gn:feature_class":"P",
    "gn:feature_code":"PPL",
    "gn:name":"Enda Ekkise",
    "gn:population":0,
    "gn:timezone":"Africa/Asmara",
    "iso:country":"ER",
    "wof:name":"Enda Ekkise",
    "wof:placetype":"locality"
},
  "geometry": {"coordinates":[39.28833,14.91917],"type":"Point"}
}