{
  "type": "Feature",
  "properties": {
    "gn:admin1_code":"04",
    "gn:asciiname":"Demba Golom",
    "gn:country_code":"ER",
    "gn:dem":1751,
    "gn:feature_class":"P",
    "gn:feature_code":"PPL",
    "gn:name":"Demba Golom",
    "gn:population":0,
    "gn:timezone":"Africa/Asmara",
    "iso:country":"ER",
    "wof:name":"Demba Golom",
    "wof:placetype":"locality"
},
  "geometry": {"coordinates":[38.6123,15.18883],"type":"Point"}
}