{
  "type": "Feature",
  "properties": {
    "gn:admin1_code":"02",
    "gn:asciiname":"Mets'alu",
    "gn:country_code":"ER",
    "gn:dem":2033,
    "gn:feature_class":"P",
    "gn:feature_code":"PPL",
    "gn:name":"Mets\u2019alu",
    "gn:population":0,
    "gn:timezone":"Africa/Asmara",
    "iso:country":"ER",
    "name:und_x_variant":[
        "Fortino Mezalu",
        "Mets\u2019alu"
    ],
    "wof:name":"Mets'alu",
    "wof:placetype":"locality"
},
  "geometry": {"coordinates":[39.05547,15.07532],"type":"Point"}
}