{
  "type": "Feature",
  "properties": {
    "gn:admin1_code":"03",
    "gn:asciiname":"Derbushet",
    "gn:country_code":"ER",
    "gn:dem":0,
    "gn:feature_class":"P",
    "gn:feature_code":"PPL",
    "gn:name":"Derbushet",
    "gn:population":0,
    "gn:timezone":"Africa/Asmara",
    "iso:country":"ER",
    "wof:name":"Derbushet",
    "wof:placetype":"locality"
},
  "geometry": {"coordinates":[40.15686,15.67547],"type":"Point"}
}