{
  "type": "Feature",
  "properties": {
    "gn:admin1_code":"04",
    "gn:asciiname":"Dembe Shetol'",
    "gn:country_code":"ER",
    "gn:dem":2049,
    "gn:feature_class":"P",
    "gn:feature_code":"PPL",
    "gn:name":"Dembe Shetol\u2019",
    "gn:population":0,
    "gn:timezone":"Africa/Asmara",
    "iso:country":"ER",
    "wof:name":"Dembe Shetol'",
    "wof:placetype":"locality"
},
  "geometry": {"coordinates":[38.65721,15.41888],"type":"Point"}
}