{
  "type": "Feature",
  "properties": {
    "gn:country":"ER",
    "gn:fcode":"PPL",
    "gn:pop":13061,
    "iso:country":"ER",
    "name:ara_x_preferred":[
        "\u0639\u062f\u064a \u0642\u064a\u062d"
    ],
    "name:azb_x_preferred":[
        "\u0627\u062f\u06cc \u06a9\u06cc\u0647"
    ],
    "name:ceb_x_preferred":[
        "Adi Keyh"
    ],
    "name:deu_x_preferred":[
        "Adi Keyh"
    ],
    "name:eng_x_preferred":[
        "Adi Keyh"
    ],
    "name:fas_x_preferred":[
        "\u02bf\u0101\u012b \u1e33\u1e25"
    ],
    "name:fin_x_preferred":[
        "Adi Keyh"
    ],
    "name:fra_x_preferred":[
        "Adi Keyh"
    ],
    "name:ita_x_preferred":[
        "Adi Keyh"
    ],
    "name:jpn_x_preferred":[
        "\u30a2\u30c7\u30a3\u30fb\u30b1\u30a4"
    ],
    "name:lit_x_preferred":[
        "Adi Keihas"
    ],
    "name:nld_x_preferred":[
        "Adi Keyh"
    ],
    "name:nob_x_preferred":[
        "Adi Keyh"
    ],
    "name:pol_x_preferred":[
        "Adi Kejh"
    ],
    "name:rus_x_preferred":[
        "\u0410\u0434\u0434\u0438-\u041a\u044d\u0439\u0438\u0445"
    ],
    "name:spa_x_preferred":[
        "Adi Keyh"
    ],
    "name:swe_x_preferred":[
        "Adi Keyh"
    ],
    "name:tir_x_preferred":[
        "\u12d3\u12f2 \u1240\u12ed\u1215"
    ],
    "name:ukr_x_preferred":[
        "\u0410\u0434\u0456-\u041a\u0435\u0457\u0445"
    ],
    "name:unk_x_variant":[
        "Adi Keih"
    ],
    "name:urd_x_preferred":[
        "\u0627\u062f\u06cc \u06a9\u06cc\u06c1"
    ],
    "name:zho_x_preferred":[
        "\u963f\u8fea\u514b\u4f0a\u8d6b"
    ],
    "qs:name":"Adi Keyh",
    "qs:photos_9r":0,
    "qs:photos_sr":0,
    "qs:pop_sr":"6",
    "wd:wordcount":104,
    "wof:name":"Adi Keyh",
    "wof:placetype":"locality",
    "wof:population":13061
},
  "geometry": {"coordinates":[39.37722,14.84444],"type":"Point"}
}