{
  "type": "Feature",
  "properties": {
    "gn:admin1_code":"06",
    "gn:asciiname":"Habrenta",
    "gn:country_code":"ER",
    "gn:dem":15,
    "gn:feature_class":"P",
    "gn:feature_code":"PPL",
    "gn:name":"Habrenta",
    "gn:population":0,
    "gn:timezone":"Africa/Asmara",
    "iso:country":"ER",
    "wof:name":"Habrenta",
    "wof:placetype":"locality"
},
  "geometry": {"coordinates":[39.60182,15.49471],"type":"Point"}
}