{
  "type": "Feature",
  "properties": {
    "gn:admin1_code":"06",
    "gn:asciiname":"Burteli",
    "gn:country_code":"ER",
    "gn:dem":15,
    "gn:feature_class":"P",
    "gn:feature_code":"PPL",
    "gn:name":"Burteli",
    "gn:population":0,
    "gn:timezone":"Africa/Asmara",
    "iso:country":"ER",
    "wof:name":"Burteli",
    "wof:placetype":"locality"
},
  "geometry": {"coordinates":[40.00715,15.36946],"type":"Point"}
}