{
  "type": "Feature",
  "properties": {
    "gn:admin1_code":"02",
    "gn:asciiname":"Addi Bezakhanays",
    "gn:country_code":"ER",
    "gn:dem":1979,
    "gn:feature_class":"P",
    "gn:feature_code":"PPL",
    "gn:name":"Addi Bezakhanays",
    "gn:population":0,
    "gn:timezone":"Africa/Asmara",
    "iso:country":"ER",
    "wof:name":"Addi Bezakhanays",
    "wof:placetype":"locality"
},
  "geometry": {"coordinates":[38.76718,15.05824],"type":"Point"}
}