{
  "type": "Feature",
  "properties": {
    "gn:admin1_code":"06",
    "gn:asciiname":"May Afide",
    "gn:country_code":"ER",
    "gn:dem":812,
    "gn:feature_class":"P",
    "gn:feature_code":"PPL",
    "gn:name":"May Afide",
    "gn:population":0,
    "gn:timezone":"Africa/Asmara",
    "iso:country":"ER",
    "wof:name":"May Afide",
    "wof:placetype":"locality"
},
  "geometry": {"coordinates":[38.12098,15.78076],"type":"Point"}
}