{
  "type": "Feature",
  "properties": {
    "gn:admin1_code":"02",
    "gn:asciiname":"Adi Hiabu",
    "gn:country_code":"ER",
    "gn:dem":1741,
    "gn:feature_class":"P",
    "gn:feature_code":"PPL",
    "gn:name":"Adi Hiabu",
    "gn:population":0,
    "gn:timezone":"Africa/Asmara",
    "iso:country":"ER",
    "name:und_x_variant":[
        "Adi Khiabu",
        "Adi Hiabu"
    ],
    "wof:name":"Adi Hiabu",
    "wof:placetype":"locality"
},
  "geometry": {"coordinates":[38.76167,14.83417],"type":"Point"}
}