{
  "type": "Feature",
  "properties": {
    "gn:admin1_code":"01",
    "gn:asciiname":"Digdig",
    "gn:country_code":"ER",
    "gn:dem":2225,
    "gn:feature_class":"P",
    "gn:feature_code":"PPL",
    "gn:name":"Digdig",
    "gn:population":0,
    "gn:timezone":"Africa/Asmara",
    "iso:country":"ER",
    "wof:name":"Digdig",
    "wof:placetype":"locality"
},
  "geometry": {"coordinates":[38.76754,15.58386],"type":"Point"}
}