{
  "type": "Feature",
  "properties": {
    "gn:admin1_code":"06",
    "gn:asciiname":"Adaito",
    "gn:country_code":"ER",
    "gn:dem":63,
    "gn:feature_class":"P",
    "gn:feature_code":"PPL",
    "gn:name":"Adaito",
    "gn:population":0,
    "gn:timezone":"Africa/Asmara",
    "iso:country":"ER",
    "name:rus_x_preferred":[
        "\u0410\u0434\u0430\u0438\u0442\u043e"
    ],
    "name:und_x_variant":[
        "Adailo",
        "Adaito"
    ],
    "wof:name":"Adaito",
    "wof:placetype":"locality"
},
  "geometry": {"coordinates":[40.37147,14.72249],"type":"Point"}
}