{
  "type": "Feature",
  "properties": {
    "gn:admin1_code":"06",
    "gn:asciiname":"Filfil",
    "gn:country_code":"ER",
    "gn:dem":873,
    "gn:feature_class":"P",
    "gn:feature_code":"PPL",
    "gn:name":"Filfil",
    "gn:population":0,
    "gn:timezone":"Africa/Asmara",
    "iso:country":"ER",
    "name:rus_x_preferred":[
        "\u0424\u0438\u043b\u044c\u0444\u0438\u043b\u044c"
    ],
    "wof:name":"Filfil",
    "wof:placetype":"locality"
},
  "geometry": {"coordinates":[38.93722,15.63444],"type":"Point"}
}