{
  "type": "Feature",
  "properties": {
    "gn:admin1_code":"05",
    "gn:asciiname":"Azzega",
    "gn:country_code":"ER",
    "gn:dem":2318,
    "gn:feature_class":"P",
    "gn:feature_code":"PPL",
    "gn:name":"Azzega",
    "gn:population":0,
    "gn:timezone":"Africa/Asmara",
    "iso:country":"ER",
    "wof:name":"Azzega",
    "wof:placetype":"locality"
},
  "geometry": {"coordinates":[38.82978,15.39842],"type":"Point"}
}