{
  "type": "Feature",
  "properties": {
    "gn:admin1_code":"02",
    "gn:asciiname":"Adi Anesti",
    "gn:country_code":"ER",
    "gn:dem":2114,
    "gn:feature_class":"P",
    "gn:feature_code":"PPL",
    "gn:name":"Adi Anesti",
    "gn:population":0,
    "gn:timezone":"Africa/Asmara",
    "iso:country":"ER",
    "wof:name":"Adi Anesti",
    "wof:placetype":"locality"
},
  "geometry": {"coordinates":[39.14712,15.0199],"type":"Point"}
}