{
  "type": "Feature",
  "properties": {
    "gn:admin1_code":"00",
    "gn:asciiname":"Per Tokar",
    "gn:cc2":"ER",
    "gn:country_code":"ER",
    "gn:dem":285,
    "gn:feature_class":"P",
    "gn:feature_code":"PPL",
    "gn:name":"Per Tokar",
    "gn:population":0,
    "gn:timezone":"Africa/Asmara",
    "iso:country":"ER",
    "name:und_x_variant":[
        "Sala",
        "Per Tokar"
    ],
    "wof:name":"Per Tokar",
    "wof:placetype":"locality"
},
  "geometry": {"coordinates":[37.46667,16.98333],"type":"Point"}
}