{
  "type": "Feature",
  "properties": {
    "gn:admin1_code":"02",
    "gn:asciiname":"Dabre",
    "gn:country_code":"ER",
    "gn:dem":1951,
    "gn:feature_class":"P",
    "gn:feature_code":"PPL",
    "gn:name":"Dabre",
    "gn:population":0,
    "gn:timezone":"Africa/Asmara",
    "iso:country":"ER",
    "wof:name":"Dabre",
    "wof:placetype":"locality"
},
  "geometry": {"coordinates":[38.55694,14.58667],"type":"Point"}
}