{
  "type": "Feature",
  "properties": {
    "gn:admin1_code":"00",
    "gn:asciiname":"Adi Amanu'el",
    "gn:country_code":"ER",
    "gn:dem":1990,
    "gn:feature_class":"P",
    "gn:feature_code":"PPL",
    "gn:name":"\u0100d\u012b \u0100manu\u2019\u0113l",
    "gn:population":0,
    "gn:timezone":"Africa/Asmara",
    "iso:country":"ER",
    "wof:name":"Adi Amanu'el",
    "wof:placetype":"locality"
},
  "geometry": {"coordinates":[38.86028,14.91083],"type":"Point"}
}