{
  "type": "Feature",
  "properties": {
    "gn:admin1_code":"06",
    "gn:asciiname":"Illauit",
    "gn:country_code":"ER",
    "gn:dem":1420,
    "gn:feature_class":"P",
    "gn:feature_code":"PPL",
    "gn:name":"Illauit",
    "gn:population":0,
    "gn:timezone":"Africa/Asmara",
    "iso:country":"ER",
    "wof:name":"Illauit",
    "wof:placetype":"locality"
},
  "geometry": {"coordinates":[39.45305,15.06606],"type":"Point"}
}