{
  "type": "Feature",
  "properties": {
    "gn:admin1_code":"06",
    "gn:asciiname":"Zariga",
    "gn:country_code":"ER",
    "gn:dem":-54,
    "gn:feature_class":"P",
    "gn:feature_code":"PPL",
    "gn:name":"Zariga",
    "gn:population":0,
    "gn:timezone":"Africa/Asmara",
    "iso:country":"ER",
    "wof:name":"Zariga",
    "wof:placetype":"locality"
},
  "geometry": {"coordinates":[40.31243,14.48676],"type":"Point"}
}