{
  "type": "Feature",
  "properties": {
    "gn:admin1_code":"02",
    "gn:asciiname":"Ad Nefas",
    "gn:country_code":"ER",
    "gn:dem":1955,
    "gn:feature_class":"P",
    "gn:feature_code":"PPL",
    "gn:name":"Ad Nefas",
    "gn:population":0,
    "gn:timezone":"Africa/Asmara",
    "iso:country":"ER",
    "name:und_x_variant":[
        "Nefas",
        "Ad Nefas"
    ],
    "wof:name":"Ad Nefas",
    "wof:placetype":"locality"
},
  "geometry": {"coordinates":[38.89528,14.69944],"type":"Point"}
}