{
  "type": "Feature",
  "properties": {
    "gn:admin1_code":"02",
    "gn:asciiname":"Ngela",
    "gn:country_code":"ER",
    "gn:dem":1707,
    "gn:feature_class":"P",
    "gn:feature_code":"PPL",
    "gn:name":"Ngela",
    "gn:population":0,
    "gn:timezone":"Africa/Asmara",
    "iso:country":"ER",
    "name:ceb_x_preferred":[
        "Ngela"
    ],
    "name:swe_x_preferred":[
        "Ngela"
    ],
    "wof:name":"Ngela",
    "wof:placetype":"locality"
},
  "geometry": {"coordinates":[39.13333,14.93333],"type":"Point"}
}