{
  "type": "Feature",
  "properties": {
    "gn:admin1_code":"03",
    "gn:asciiname":"Pharon",
    "gn:country_code":"ER",
    "gn:dem":13,
    "gn:feature_class":"P",
    "gn:feature_code":"PPL",
    "gn:name":"Pharon",
    "gn:population":0,
    "gn:timezone":"Africa/Asmara",
    "iso:country":"ER",
    "name:und_x_variant":[
        "Faraon",
        "Faroon"
    ],
    "wof:name":"Pharon",
    "wof:placetype":"locality"
},
  "geometry": {"coordinates":[40.70006,14.86188],"type":"Point"}
}