{
  "type": "Feature",
  "properties": {
    "gn:admin1_code":"06",
    "gn:asciiname":"Basheri",
    "gn:country_code":"ER",
    "gn:dem":1285,
    "gn:feature_class":"P",
    "gn:feature_code":"PPL",
    "gn:name":"Basheri",
    "gn:population":0,
    "gn:timezone":"Africa/Asmara",
    "iso:country":"ER",
    "wof:name":"Basheri",
    "wof:placetype":"locality"
},
  "geometry": {"coordinates":[38.46278,15.87234],"type":"Point"}
}